{"薄暮報恨者":[{},1],"王朝毀滅者":[{},1],"狩龍之斧":[{},1],"貝希莫斯巨叉":[{"結晶-A級":254,"寶石-A級":100,"貝希莫斯巨叉碎片":20,"高級軟皮":52,"合成的炭焦":104,"米索莉合金":208,"恩尼亞":52,"巨匠骨架":15,"強化金屬板":208},1],"末日毀滅者":[{"結晶-A級":193,"寶石-A級":74,"末日毀滅者金屬塊":20,"高級軟皮":37,"合成的炭焦":74,"米索莉合金":148,"恩尼亞":37,"巨匠骨架":18,"強化金屬板":148},1],"破壞者巨鎚":[{"結晶-B級":222,"寶石-B級":143,"破壞者巨鎚組件":20,"高級軟皮":21,"合成的炭焦":42,"米索莉合金":84,"恩尼亞":21,"巨匠骨架":13,"強化金屬板":84},1],"星爆":[{},1],"暴風雪巨鎚":[{},1],"矮人巨鎚":[{},1],"卡拉克衝角":[{},1],"下巨人之鎚":[{"結晶-D級":430,"寶石-D級":139,"下巨人之鎚組件":7,"炭焦":88,"鐵":176,"高級軟皮":44},1],"赫利奧斯鉋刀":[{},1],"幻靈鉋刀":[{},1],"英啟鉋刀":[{},1],"鎮魂鉋刀":[{},1],"薄暮鉋刀":[{},1],"伊克魯斯分解者":[{},1],"王朝小刀":[{},1],"天使殺手":[{},1],"那卡風暴":[{"結晶-A級":254,"寶石-A級":100,"那卡風暴碎片":20,"合成的炭焦":204,"米索莉合金":204,"恩尼亞":102,"刀匠鑄模":10,"強化金屬板":102},1],"魂體分離器":[{"結晶-A級":161,"寶石-A級":74,"魂體分離器的刀身":29,"合成的炭焦":156,"米索莉合金":156,"恩尼亞":78,"刀匠鑄模":7,"強化金屬板":78},1],"血腥之蘭":[{"結晶-B級":193,"寶石-B級":143,"血腥之蘭的刀身":25,"合成的炭焦":82,"米索莉合金":82,"恩尼亞":41,"刀匠鑄模":5,"強化金屬板":41},1],"惡魔短劍":[{"製作卷軸(惡魔短劍100%)":1,"結晶-B級":341,"寶石-B級":98,"惡魔短劍的刀身":13,"合成的炭焦":172,"米索莉合金":172,"恩尼亞":86,"刀匠鑄模":2},1],"波形刃":[{"製作卷軸(波形刃100%)":1,"結晶-C級":517,"寶石-B級":62,"波形刃的刀身":12,"合成的炭焦":114,"米索莉合金":114,"恩尼亞":57,"刀匠鑄模":2},1],"地獄刀":[{"製作卷軸(地獄刀100%)":1,"結晶-C級":517,"寶石-B級":62,"地獄刀的刀身":12,"合成的炭焦":114,"米索莉合金":114,"恩尼亞":57,"刀匠鑄模":2},1],"水晶匕首":[{"結晶-C級":410,"寶石-C級":248,"水晶匕首的刀身":11,"合成的炭焦":76,"米索莉合金":76,"工匠模具":2,"金屬強化劑":152},1],"優雅匕首":[{"結晶-C級":300,"寶石-C級":166,"優雅匕首的刀身":10,"合成的炭焦":50,"米索莉合金":50,"工匠模具":2,"金屬強化劑":100},1],"黑暗狂嘯者":[{"結晶-C級":300,"寶石-C級":166,"黑暗狂嘯者的刀身":10,"合成的炭焦":50,"米索莉合金":50,"工匠模具":2,"金屬強化劑":100},1],"袖珍刀":[{"結晶-C級":180,"寶石-C級":105,"袖珍刀的刀身":9,"合成的炭焦":33,"米索莉合金":33,"工匠模具":2,"金屬強化劑":66},1],"魔炎匕首":[{"結晶-C級":180,"寶石-C級":105,"魔炎匕首的刀身":9,"合成的炭焦":33,"米索莉合金":33,"工匠模具":2,"金屬強化劑":66},1],"受詛咒的匕首":[{"結晶-D級":700,"寶石-C級":81,"受詛咒匕首的刀身":8,"合成的炭焦":25,"米索莉合金":25,"工匠模具":2,"金屬強化劑":50},1],"狼之針":[{"狼之針的刀緣":8,"結晶-D級":700,"寶石-C級":81,"合成的炭焦":25,"米索莉合金":25,"工匠模具":2,"金屬強化劑":50},1],"黑暗精靈匕首":[{"結晶-D級":700,"寶石-C級":81,"黑暗精靈匕首的刀緣":8,"合成的炭焦":25,"米索莉合金":25,"工匠模具":2,"金屬強化劑":50},1],"米索莉匕首":[{"結晶-D級":550,"寶石-D級":185,"米索莉匕首的刀身":8,"炭焦":220,"鐵":220,"鐵鑄模":2},1],"突刺刀":[{"結晶-D級":430,"寶石-D級":139,"突刺刀的刀緣":7,"炭焦":175,"鐵":175,"鐵鑄模":2},1],"受詛咒的突刺刀":[{"結晶-D級":430,"寶石-D級":139,"受詛咒的突刺刀刀緣":7,"炭焦":175,"鐵":175,"鐵鑄模":2},1],"森林神之刀":[{"結晶-D級":300,"寶石-D級":91,"森林神之刀的刀身":6,"炭焦":118,"鐵":118,"鐵鑄模":2},1],"刺客刀":[{"寶石-D級":34,"刺客刀的刀身":4,"炭焦":70,"鐵":70,"鐵鑄模":2},1],"碎劍者":[{"碎劍者的劍身":3,"鋼鐵礦":365,"煤礦":365},1],"短刀":[{"短刀的刀身":2,"鋼鐵礦":80,"煤礦":80},1],"小刀":[{},1],"匕首":[{"結晶-D級":550,"寶石-D級":185,"米索莉匕首的刀身":8,"炭焦":220,"鐵":220,"鐵鑄模":2},1],"赫利奧斯術杖":[{},1],"幻靈術杖":[{},1],"英啟術杖":[{},1],"鎮魂術杖":[{},1],"伊克魯斯手杖":[{},1],"薄暮術杖":[{},1],"王朝釘鎚":[{},1],"祕儀權杖":[{},1],"卡布里歐之手":[{"結晶-A級":254,"寶石-A級":100,"卡布里歐之手金屬塊":20,"顆粒狀的骨粉":212,"合成的絞線":106,"奧里哈魯根":106,"恩尼亞":106,"巨匠骨架":15,"強化金屬板":212},1],"火龍之首":[{"結晶-A級":194,"寶石-A級":74,"火龍之首組件":20,"高級軟皮":49,"合成的炭焦":98,"米索莉合金":98,"恩尼亞":49,"巨匠骨架":18,"強化金屬板":196},1],"英魂之眼":[{"結晶-B級":215,"寶石-B級":143,"英魂之眼組件":20,"高級軟皮":30,"合成的炭焦":60,"米索莉合金":60,"恩尼亞":30,"巨匠骨架":12,"強化金屬板":120},1],"卡倚巴奴之骨":[{},1],"破咒者":[{},1],"月蝕斧":[{},1],"永恆手杖":[{"結晶-C級":300,"寶石-C級":166,"永恆手杖的金屬塊":10,"顆粒狀的骨粉":74,"合成的絞線":37,"奧里哈魯根":37,"金屬強化劑":111},1],"自然之棍":[{"結晶-C級":300,"寶石-C級":166,"自然之棍的金屬塊":10,"顆粒狀的骨粉":74,"合成的絞線":37,"奧里哈魯根":37,"金屬強化劑":111},1],"底獄之鎚":[{"結晶-C級":300,"寶石-C級":166,"底獄之鎚的金屬塊":10,"高級軟皮":27,"合成的炭焦":54,"米索莉合金":54,"金屬強化劑":108},1],"信仰手杖":[{"結晶-D級":700,"寶石-C級":81,"信仰手杖的柄":8,"顆粒狀的骨粉":40,"合成的絞線":20,"奧里哈魯根":20,"金屬強化劑":60},1],"生命手杖":[{"結晶-D級":550,"寶石-D級":185,"生命手杖的柄":8,"絞線":130,"鐵":130,"顆粒狀的骨粉":260},1],"祭司釘鎚":[{},1],"審判之鎚":[{"結晶-D級":200,"寶石-D級":57,"審判之鎚的刀身":5,"炭焦":60,"鐵":60,"高級軟皮":30},1],"赫利奧斯復仇者":[{},1],"幻靈復仇者":[{},1],"英啟復仇者":[{},1],"鎮魂復仇者":[{},1],"薄暮復仇者":[{},1],"伊克魯斯之鎚":[{},1],"王朝戰鎚":[{},1],"玄武岩戰鎚":[{},1],"貝拉凱爾聖斧":[{"結晶-A級":254,"寶石-A級":100,"貝拉凱爾聖斧碎片":20,"高級軟皮":68,"合成的炭焦":136,"米索莉合金":136,"恩尼亞":68,"巨匠骨架":15,"強化金屬板":272},1],"樂園":[{"結晶-A級":194,"寶石-A級":74,"樂園的金屬塊":30,"高級軟皮":49,"合成的炭焦":98,"米索莉合金":98,"恩尼亞":49,"巨匠骨架":10,"強化金屬板":196},1],"流星雨":[{"結晶-B級":215,"寶石-B級":143,"流星雨的金屬塊":25,"高級軟皮":30,"合成的炭焦":60,"米索莉合金":60,"恩尼亞":30,"巨匠骨架":7,"強化金屬板":120},1],"亡者榮譽":[{"製作卷軸(亡者榮譽100%)":1,"結晶-B級":339,"寶石-B級":98,"亡者榮譽的石材":13,"高級軟皮":86,"合成的炭焦":172,"米索莉合金":172,"恩尼亞":86,"巨匠骨架":3},1],"工藝戰斧":[{"製作卷軸(工藝戰斧100%)":1,"結晶-B級":339,"寶石-B級":98,"工藝戰斧的刀身":13,"高級軟皮":86,"合成的炭焦":172,"米索莉合金":172,"恩尼亞":86,"巨匠骨架":3},1],"巨大戰斧":[{"製作卷軸(巨大戰斧100%)":1,"結晶-C級":498,"寶石-B級":62,"巨大戰斧的金屬塊":12,"高級軟皮":59,"合成的炭焦":118,"米索莉合金":118,"恩尼亞":59,"巨匠骨架":3},1],"夜叉釘鎚":[{"結晶-C級":410,"寶石-C級":248,"夜叉釘鎚的金屬塊":11,"高級軟皮":40,"合成的炭焦":80,"米索莉合金":80,"金屬強化劑":160},1],"巨戰斧":[{"結晶-C級":300,"寶石-C級":166,"巨戰斧的刀身":10,"高級軟皮":27,"合成的炭焦":54,"米索莉合金":54,"金屬強化劑":108},1],"夢想斧":[{"結晶-C級":300,"寶石-C級":166,"夢想斧的刀身":10,"高級軟皮":27,"合成的炭焦":54,"米索莉合金":54,"金屬強化劑":108},1],"矮人戰鎚":[{"結晶-C級":180,"寶石-C級":105,"矮人戰鎚的金屬塊":9,"高級軟皮":19,"合成的炭焦":38,"米索莉合金":38,"金屬強化劑":76},1],"重鎚":[{"結晶-D級":700,"寶石-C級":81,"重鎚的金屬塊":8,"高級軟皮":15,"合成的炭焦":30,"米索莉合金":30,"金屬強化劑":60},1],"戰斧":[{"結晶-D級":700,"寶石-C級":81,"戰斧的金屬塊":8,"高級軟皮":15,"合成的炭焦":30,"米索莉合金":30,"金屬強化劑":60},1],"戰錐":[{"結晶-D級":700,"寶石-C級":81,"戰錐的金屬塊":8,"高級軟皮":15,"合成的炭焦":30,"米索莉合金":30,"金屬強化劑":60},1],"顱骨雕刻者":[{"結晶-D級":700,"寶石-C級":81,"顱骨雕刻者的金屬塊":8,"高級軟皮":15,"合成的炭焦":30,"米索莉合金":30,"金屬強化劑":60},1],"碎骨者":[{"結晶-D級":550,"寶石-D級":185,"碎骨者的金屬塊":8,"炭焦":160,"鐵":160,"高級軟皮":80},1],"流星鎚":[{"結晶-D級":430,"寶石-D級":139,"流星鎚的金屬塊":7,"炭焦":128,"鐵":128,"高級軟皮":64},1],"塔巴曲刃斧":[{"結晶-D級":430,"寶石-D級":139,"塔巴曲刃斧的金屬塊":7,"炭焦":128,"鐵":128,"高級軟皮":64},1],"頭顱破壞者":[{"結晶-D級":430,"寶石-D級":139,"頭顱破壞者的金屬塊":7,"炭焦":128,"鐵":128,"高級軟皮":64},1],"巨大骨棒":[{"結晶-D級":430,"寶石-D級":139,"巨大骨棒的金屬塊":7,"炭焦":128,"鐵":128,"高級軟皮":64},1],"山羊頭之杖":[{"結晶-D級":430,"寶石-D級":139,"山羊頭之杖的金屬塊":7,"絞線":100,"鐵":100,"顆粒狀的骨粉":200},1],"狼牙棒":[{"結晶-D級":300,"寶石-D級":91,"狼牙棒的金屬塊":6,"炭焦":90,"鐵":90,"高級軟皮":45},1],"鋼鎚":[{"鋼鎚的金屬塊":3,"軟皮":130,"鋼鐵礦":260,"煤礦":260},1],"骨棒":[{"結晶-D級":430,"寶石-D級":139,"巨大骨棒的金屬塊":7,"炭焦":128,"鐵":128,"高級軟皮":64},1],"鐮刀":[{"結晶-D級":700,"寶石-C級":81,"大鐮刀的刀緣":8,"高級軟皮":10,"合成的炭焦":20,"米索莉合金":40,"金屬強化劑":50},1],"釘鎚":[{"結晶-D級":550,"寶石-D級":185,"阿吐巴釘鎚的金屬塊":8,"炭焦":110,"鐵":220,"高級軟皮":55},1],"赫利奧斯殺刃":[{},1],"幻靈殺刃":[{},1],"英啟殺刃":[{},1],"鎮魂殺刃":[{},1],"伊克魯斯重兵刃":[{},1],"薄暮殺刃":[{},1],"王朝之刃":[{},1],"天國審判":[{},1],"伊波斯巨劍":[{"結晶-A級":254,"寶石-A級":100,"伊波斯巨劍劍身":20,"合成的炭焦":113,"米索莉合金":226,"恩尼亞":113,"刀匠鑄模":11,"強化金屬板":113},1],"斬龍刀":[{"結晶-A級":195,"寶石-A級":74,"斬龍刀的刀身":29,"合成的炭焦":78,"米索莉合金":156,"恩尼亞":78,"刀匠鑄模":7,"強化金屬板":78},1],"煉獄之主":[{"結晶-B級":230,"寶石-B級":143,"煉獄之主刃部":20,"合成的炭焦":40,"米索莉合金":80,"恩尼亞":40,"刀匠鑄模":8,"強化金屬板":40},1],"守護神之劍":[{},1],"巨劍":[{"製作卷軸(巨劍100%)":1,"結晶-C級":317,"寶石-B級":62,"巨劍的刀身":12,"合成的炭焦":63,"米索莉合金":126,"恩尼亞":63,"刀匠鑄模":3},1],"狂戰士之刃":[{"結晶-C級":375,"寶石-C級":248,"狂戰士之刃的刀身":11,"合成的炭焦":43,"米索莉合金":86,"工匠模具":3,"金屬強化劑":172},1],"帕格立歐之劍":[{},1],"焰形劍":[{"結晶-D級":700,"寶石-C級":81,"焰形劍的劍身":8,"合成的炭焦":12,"米索莉合金":24,"工匠模具":3,"金屬強化劑":48},1],"雙刃大砍刀":[{"結晶-D級":550,"寶石-D級":185,"雙刃大砍刀的刀身":8,"炭焦":135,"鐵":270,"鐵鑄模":3},1],"下巨人之劍":[{},1],"重型劍":[{"結晶-D級":117,"寶石-D級":34,"重型劍的刀身":4,"炭焦":30,"鐵":60,"鐵鑄模":3},1],"鋼劍":[{"結晶-D級":117,"寶石-D級":34,"鋼劍劍身":4,"炭焦":30,"鐵":60,"鐵鑄模":3},1],"雙手劍":[{"結晶-D級":300,"寶石-D級":91,"雙手劍的劍身":6,"炭焦":72,"鐵":144,"鐵鑄模":3},1],"刺擊刀":[{"刺擊刀的刀身":2,"鋼鐵礦":110,"煤礦":55},1],"赫利奧斯爆刃":[{},1],"幻靈爆刃":[{},1],"英啟爆刃":[{},1],"鎮魂爆刃":[{},1],"薄暮爆刃":[{},1],"伊克魯斯之靈":[{},1],"王朝幻影劍":[{},1],"緹米絲之舌":[{"結晶-A級":254,"寶石-A級":100,"緹米絲之舌碎片":20,"合成的炭焦":204,"米索莉合金":204,"恩尼亞":102,"刀匠鑄模":10,"強化金屬板":102},1],"奇蹟劍":[{"結晶-A級":152,"寶石-A級":74,"奇蹟劍的刀身":32,"合成的炭焦":160,"米索莉合金":160,"恩尼亞":80,"刀匠鑄模":6,"強化金屬板":80},1],"元素劍":[{"結晶-B級":193,"寶石-B級":143,"元素劍的刀身":25,"合成的炭焦":82,"米索莉合金":82,"恩尼亞":41,"刀匠鑄模":5,"強化金屬板":41},1],"巫師之淚":[{},1],"聖堂之劍":[{"製作卷軸(聖堂之劍100%)":1,"結晶-C級":517,"寶石-B級":62,"聖堂之劍的刀身":12,"合成的炭焦":114,"米索莉合金":114,"恩尼亞":57,"刀匠鑄模":2},1],"日蝕劍":[{},1],"何門奎思之劍":[{"結晶-C級":300,"寶石-C級":166,"何門奎思之劍的劍身":10,"合成的炭焦":50,"米索莉合金":50,"工匠模具":2,"金屬強化劑":100},1],"死息之劍":[{"結晶-C級":300,"寶石-C級":166,"死息之劍的劍身":10,"合成的炭焦":50,"米索莉合金":50,"工匠模具":2,"金屬強化劑":100},1],"奧祕之刃":[{},1],"魔霧之劍":[{},1],"祭司之劍":[{},1],"赫利奧斯切刃":[{},1],"幻靈切刃":[{},1],"英啟切刃":[{},1],"鎮魂切刃":[{},1],"薄暮切刃":[{},1],"伊克魯斯之劍":[{},1],"王朝劍":[{},1],"忘卻之刃":[{},1],"希露冰刃":[{},1],"黑暗軍刀":[{"結晶-A級":161,"寶石-A級":74,"黑暗軍刀的刀身":29,"合成的炭焦":156,"米索莉合金":156,"恩尼亞":78,"刀匠鑄模":7,"強化金屬板":78},1],"塔魯刀":[{"結晶-B級":192,"寶石-B級":143,"塔魯刀的刀身":25,"合成的炭焦":82,"米索莉合金":82,"恩尼亞":41,"刀匠鑄模":5,"強化金屬板":41},1],"大馬士革刀":[{"製作卷軸(大馬士革刀100%)":1,"結晶-B級":341,"寶石-B級":98,"大馬士革刀的劍身":13,"合成的炭焦":172,"米索莉合金":172,"恩尼亞":86,"刀匠鑄模":2},1],"柯貝克劍":[{"製作卷軸(柯貝克劍100%)":1,"結晶-C級":517,"寶石-B級":62,"柯貝克劍的劍身":12,"合成的炭焦":114,"米索莉合金":114,"恩尼亞":57,"刀匠鑄模":2},1],"瑟魯基長劍":[{"結晶-C級":410,"寶石-C級":248,"瑟魯基長劍的劍身":11,"合成的炭焦":41,"米索莉合金":82,"工匠模具":3,"金屬強化劑":164},1],"卡里埔士劍":[{"結晶-C級":300,"寶石-C級":166,"卡里埔士劍的劍身":10,"合成的炭焦":50,"米索莉合金":50,"工匠模具":2,"金屬強化劑":100},1],"迷惑之劍":[{"結晶-C級":300,"寶石-C級":166,"迷惑之劍的劍身":10,"合成的炭焦":50,"米索莉合金":50,"工匠模具":2,"金屬強化劑":100},1],"大和劍":[{"結晶-C級":300,"寶石-C級":166,"大和劍的劍身":10,"合成的炭焦":50,"米索莉合金":50,"工匠模具":2,"金屬強化劑":100},1],"極限之劍":[{"結晶-C級":300,"寶石-C級":166,"極限之劍的劍身":10,"合成的炭焦":50,"米索莉合金":50,"工匠模具":2,"金屬強化劑":100},1],"夢魘劍":[{"結晶-C級":300,"寶石-C級":166,"夢魘劍的劍身":10,"合成的炭焦":50,"米索莉合金":50,"工匠模具":2,"金屬強化劑":100},1],"彎刀":[{"結晶-C級":180,"寶石-C級":105,"彎刀的刀身":9,"合成的炭焦":33,"米索莉合金":33,"工匠模具":2,"金屬強化劑":66},1],"武士刀":[{"結晶-C級":180,"寶石-C級":105,"武士刀的刀身":9,"合成的炭焦":33,"米索莉合金":33,"工匠模具":2,"金屬強化劑":66},1],"靈魂之劍":[{"結晶-C級":180,"寶石-C級":105,"靈魂之劍的劍身":9,"合成的炭焦":33,"米索莉合金":33,"工匠模具":2,"金屬強化劑":66},1],"襲擊劍":[{"結晶-C級":180,"寶石-C級":105,"襲擊劍的劍身":9,"合成的炭焦":33,"米索莉合金":33,"工匠模具":2,"金屬強化劑":66},1],"暴風之劍":[{"結晶-D級":700,"寶石-C級":81,"暴風之劍的劍身":8,"合成的炭焦":25,"米索莉合金":25,"工匠模具":2,"金屬強化劑":50},1],"精靈長劍":[{"結晶-D級":550,"寶石-D級":185,"精靈長劍的劍身":8,"炭焦":220,"鐵":220,"鐵鑄模":2},1],"革命劍":[{"結晶-D級":430,"寶石-D級":139,"革命劍的劍身":7,"炭焦":175,"鐵":175,"鐵鑄模":2},1],"椎骨之劍":[{"結晶-D級":200,"寶石-D級":57,"椎骨之劍的劍身":5,"炭焦":75,"鐵":75,"鐵鑄模":2},1],"軍刀":[{"寶石-D級":34,"軍刀的刀身":4,"炭焦":70,"鐵":70,"鐵鑄模":2},1],"長劍":[{"結晶-C級":410,"寶石-C級":248,"瑟魯基長劍的劍身":11,"合成的炭焦":41,"米索莉合金":82,"工匠模具":3,"金屬強化劑":164},1],"反射劍":[{"反射劍的劍身":3,"鋼鐵礦":200,"煤礦":200},1],"寬劍":[{"寬劍的劍身":1,"鋼鐵礦":18,"煤礦":18},1],"短劍":[{"製作卷軸(惡魔短劍100%)":1,"結晶-B級":341,"寶石-B級":98,"惡魔短劍的刀身":13,"合成的炭焦":172,"米索莉合金":172,"恩尼亞":86,"刀匠鑄模":2},1],"伊克魯斯翼刃":[{},1],"赫利奧斯射靈":[{},1],"幻靈射靈":[{},1],"英啟射靈":[{},1],"鎮魂射靈":[{},1],"赫利奧斯報恨者":[{},1],"幻靈報恨者":[{},1],"英啟報恨者":[{},1],"鎮魂報恨者":[{},1],"薄暮詩杖":[{},1],"王朝魔杖":[{},1],"帝國權杖":[{},1],"惡魔結晶":[{"結晶-A級":254,"寶石-A級":100,"惡魔結晶碎片":20,"顆粒狀的骨粉":212,"合成的絞線":106,"奧里哈魯根":106,"恩尼亞":106,"巨匠骨架":15,"強化金屬板":212},1],"世界樹樹枝":[{"結晶-A級":193,"寶石-A級":74,"世界樹樹枝的金屬塊":29,"顆粒狀的骨粉":154,"合成的絞線":77,"奧里哈魯根":77,"恩尼亞":77,"巨匠骨架":10,"強化金屬板":154},1],"帕黎恩魔杖":[{"結晶-B級":216,"寶石-B級":143,"帕黎恩魔杖的金屬塊":25,"顆粒狀的骨粉":94,"合成的絞線":47,"奧里哈魯根":47,"恩尼亞":47,"巨匠骨架":7,"強化金屬板":94},1],"邪靈魔杖":[{"製作卷軸(邪靈魔杖100%)":1,"結晶-B級":342,"寶石-B級":98,"邪靈魔杖的金屬塊":13,"顆粒狀的骨粉":216,"合成的絞線":108,"奧里哈魯根":108,"恩尼亞":108,"巨匠骨架":3},1],"精靈魔杖":[{"製作卷軸(精靈魔杖100%)":1,"結晶-C級":491,"寶石-B級":62,"精靈魔杖的金屬塊":12,"顆粒狀的骨粉":150,"合成的絞線":75,"奧里哈魯根":75,"恩尼亞":75,"巨匠骨架":3},1],"亡者魔杖":[{"結晶-C級":410,"寶石-C級":248,"亡者魔杖的金屬塊":11,"顆粒狀的骨粉":108,"合成的絞線":54,"奧里哈魯根":54,"金屬強化劑":162},1],"食屍鬼魔杖":[{"結晶-C級":410,"寶石-C級":248,"食屍鬼魔杖的金屬塊":11,"顆粒狀的骨粉":108,"合成的絞線":54,"奧里哈魯根":54,"金屬強化劑":162},1],"惡魔魔杖":[{"結晶-C級":410,"寶石-C級":248,"惡魔魔杖的金屬塊":11,"顆粒狀的骨粉":108,"合成的絞線":54,"奧里哈魯根":54,"金屬強化劑":162},1],"帕格立歐之斧":[{"結晶-C級":330,"寶石-C級":187,"帕格立歐之斧的刀身":10,"高級軟皮":20,"合成的炭焦":40,"米索莉合金":80,"金屬強化劑":100},1],"佩勒迪亞魔杖":[{"結晶-C級":300,"寶石-C級":166,"佩勒迪亞魔杖的金屬塊":10,"顆粒狀的骨粉":74,"合成的絞線":37,"奧里哈魯根":37,"金屬強化劑":111},1],"地獄魔杖":[{"結晶-C級":300,"寶石-C級":166,"地獄魔杖的金屬塊":10,"顆粒狀的骨粉":74,"合成的絞線":37,"奧里哈魯根":37,"金屬強化劑":111},1],"帕格立歐之鎚":[{"結晶-C級":300,"寶石-C級":166,"帕格立歐之鎚的金屬塊":10,"高級軟皮":18,"合成的炭焦":36,"米索莉合金":72,"金屬強化劑":90},1],"賢者魔杖":[{"結晶-C級":300,"寶石-C級":166,"賢者魔杖的金屬塊":10,"顆粒狀的骨粉":74,"合成的絞線":37,"奧里哈魯根":37,"金屬強化劑":111},1],"受詛咒的魔杖":[{"結晶-C級":180,"寶石-C級":105,"受詛咒魔杖的金屬塊":9,"顆粒狀的骨粉":52,"合成的絞線":26,"奧里哈魯根":26,"金屬強化劑":78},1],"巨大末日鎚":[{"結晶-D級":700,"寶石-C級":81,"巨大末日鎚的金屬塊":8,"高級軟皮":10,"合成的炭焦":20,"米索莉合金":40,"金屬強化劑":50},1],"水晶魔杖":[{"結晶-D級":700,"寶石-C級":81,"水晶魔杖的金屬塊":8,"顆粒狀的骨粉":40,"合成的絞線":20,"奧里哈魯根":20,"金屬強化劑":60},1],"巨大末日斧":[{"結晶-D級":700,"寶石-C級":81,"巨大末日斧的刀身":8,"高級軟皮":10,"合成的炭焦":20,"米索莉合金":40,"金屬強化劑":50},1],"阿吐巴鎚":[{"結晶-D級":550,"寶石-D級":185,"阿吐巴鎚的金屬塊":8,"炭焦":110,"鐵":220,"高級軟皮":55},1],"魂靈魔杖":[{"結晶-D級":550,"寶石-D級":185,"魂靈魔杖的金屬塊":8,"絞線":130,"鐵":130,"顆粒狀的骨粉":260},1],"阿吐巴釘鎚":[{"結晶-D級":550,"寶石-D級":185,"阿吐巴釘鎚的金屬塊":8,"炭焦":110,"鐵":220,"高級軟皮":55},1],"法咒魔杖":[{"結晶-D級":200,"寶石-D級":57,"法咒魔杖的金屬塊":5,"絞線":45,"鐵":45,"顆粒狀的骨粉":90},1],"柏木魔杖":[{"柏木魔杖的金屬塊":2,"樹枝":55,"鋼鐵礦":55,"動物的骨頭":110},1],"柳木魔杖":[{"柳木魔杖的金屬塊":1,"樹枝":12,"鋼鐵礦":12,"動物的骨頭":24},1],"伊克魯斯刺劍":[{},1],"刺劍":[{},1],"赫利奧斯投弓":[{},1],"幻靈投弓":[{},1],"英啟投弓":[{},1],"鎮魂投弓":[{},1],"薄暮投弓":[{},1],"伊克魯斯之弓":[{},1],"王朝弓":[{},1],"紅龍之弓":[{},1],"夏伊德獵弓":[{"結晶-A級":254,"寶石-A級":100,"夏伊德獵弓柄":20,"高級軟皮":68,"合成的絞線":68,"米索莉合金":340,"恩尼亞":68,"巨匠骨架":15,"強化金屬板":136},1],"靈魂弓":[{"結晶-A級":197,"寶石-A級":74,"靈魂弓的柄":29,"高級軟皮":49,"合成的絞線":49,"米索莉合金":245,"恩尼亞":49,"巨匠骨架":10,"強化金屬板":98},1],"顱之弓":[{"結晶-B級":219,"寶石-B級":143,"顱之弓的柄":25,"高級軟皮":30,"合成的絞線":30,"米索莉合金":150,"恩尼亞":30,"巨匠骨架":7,"強化金屬板":60},1],"冒險弓":[{"製作卷軸(冒險弓100%)":1,"結晶-B級":328,"寶石-B級":98,"冒險弓的柄":13,"高級軟皮":57,"合成的絞線":57,"米索莉合金":285,"恩尼亞":57,"巨匠骨架":3},1],"黑暗精靈長弓":[{"製作卷軸(黑暗精靈長弓100%)":1,"結晶-C級":534,"寶石-B級":62,"黑暗精靈長弓的柄":12,"高級軟皮":37,"合成的絞線":37,"米索莉合金":185,"恩尼亞":37,"巨匠骨架":3},1],"卓越弓":[{"結晶-C級":420,"寶石-C級":248,"卓越弓的柄":11,"高級軟皮":24,"合成的絞線":24,"米索莉合金":120,"金屬強化劑":144},1],"阿卡特長弓":[{"結晶-C級":290,"寶石-C級":166,"阿卡特長弓的柄":10,"高級軟皮":17,"合成的絞線":17,"米索莉合金":85,"金屬強化劑":102},1],"元素弓":[{"結晶-C級":170,"寶石-C級":105,"元素弓的柄":9,"高級軟皮":12,"合成的絞線":12,"米索莉合金":60,"金屬強化劑":72},1],"高級精靈弓":[{"結晶-C級":170,"寶石-C級":105,"高級精靈弓的金屬塊":9,"高級軟皮":12,"合成的絞線":12,"米索莉合金":60,"金屬強化劑":72},1],"冰晶弓":[{"結晶-D級":700,"寶石-C級":81,"冰晶弓的柄":8,"高級軟皮":9,"合成的絞線":9,"米索莉合金":45,"金屬強化劑":54},1],"風暴弓":[{"結晶-D級":550,"寶石-D級":185,"風暴弓的柄":8,"絞線":55,"鐵":275,"高級軟皮":55},1],"強化長弓":[{"結晶-D級":300,"寶石-D級":139,"強化長弓的柄":7,"絞線":45,"鐵":225,"高級軟皮":45},1],"腰弩":[{"結晶-D級":300,"寶石-D級":91,"腰弩的柄":6,"絞線":30,"鐵":150,"高級軟皮":30},1],"長弓":[{"結晶-D級":300,"寶石-D級":139,"強化長弓的柄":7,"絞線":45,"鐵":225,"高級軟皮":45},1],"精靈弓":[{"結晶-D級":200,"寶石-D級":57,"精靈弓的柄":5,"絞線":20,"鐵":100,"高級軟皮":20},1],"合金弓":[{"合金弓的柄":3,"軟皮":80,"鋼鐵礦":400,"絞線":80},1],"森林弓":[{"森林弓的柄":3,"軟皮":45,"鋼鐵礦":225,"絞線":45},1],"弓":[{"弓的金屬塊":1,"軟皮":4,"鋼鐵礦":20,"絞線":4},1],"赫利奧斯戰爪":[{},1],"幻靈戰爪":[{},1],"英啟戰爪":[{},1],"鎮魂戰爪":[{},1],"薄暮戰爪":[{},1],"伊克魯斯之手":[{},1],"王朝拳套爪":[{},1],"惡魔獵爪":[{},1],"索貝克颶風":[{"結晶-A級":254,"寶石-A級":100,"索貝克颶風刀緣":20,"高級軟皮":68,"合成的炭焦":136,"米索莉合金":136,"恩尼亞":68,"巨匠骨架":15,"強化金屬板":272},1],"龍牙":[{"結晶-A級":194,"寶石-A級":74,"龍牙的刀身":30,"高級軟皮":49,"合成的炭焦":98,"米索莉合金":98,"恩尼亞":49,"巨匠骨架":10,"強化金屬板":196},1],"血旋風":[{"結晶-B級":215,"寶石-B級":143,"血旋風的刀身":25,"高級軟皮":30,"合成的炭焦":60,"米索莉合金":60,"恩尼亞":30,"巨匠骨架":7,"強化金屬板":120},1],"博利恩拳套":[{"製作卷軸(博利恩拳套100%)":1,"結晶-B級":339,"寶石-B級":98,"博利恩拳套的刃部":13,"高級軟皮":86,"合成的炭焦":172,"米索莉合金":172,"恩尼亞":86,"巨匠骨架":3},1],"帕塔拳刃":[{"結晶-C級":410,"寶石-C級":248,"巨型帕塔拳刃的刀身":11,"高級軟皮":40,"合成的炭焦":80,"米索莉合金":80,"金屬強化劑":160},1],"阿斯拉爪":[{"製作卷軸(阿斯拉爪100%)":1,"結晶-C級":498,"寶石-B級":62,"阿斯拉爪的刀身":12,"高級軟皮":59,"合成的炭焦":118,"米索莉合金":118,"恩尼亞":59,"巨匠骨架":3},1],"巨型帕塔拳刃":[{"結晶-C級":410,"寶石-C級":248,"巨型帕塔拳刃的刀身":11,"高級軟皮":40,"合成的炭焦":80,"米索莉合金":80,"金屬強化劑":160},1],"拳刃":[{"結晶-C級":300,"寶石-C級":166,"拳刃的刀身":10,"高級軟皮":27,"合成的炭焦":54,"米索莉合金":54,"金屬強化劑":108},1],"關節拳":[{"結晶-C級":200,"寶石-C級":105,"關節拳的刃":9,"高級軟皮":27,"合成的炭焦":54,"米索莉合金":54},1],"圓月輪":[{"結晶-D級":700,"寶石-C級":81,"圓月輪的刀緣":8,"高級軟皮":15,"合成的炭焦":30,"米索莉合金":30,"金屬強化劑":60},1],"波浪刀":[{"結晶-D級":550,"寶石-D級":185,"波浪刀的刀緣":8,"炭焦":160,"鐵":160,"高級軟皮":80},1],"拳套刀":[{"結晶-D級":430,"寶石-D級":139,"拳套刀的刀緣":7,"炭焦":128,"鐵":128,"高級軟皮":64},1],"拳套爪":[{},1],"赫利奧斯風暴者":[{},1],"幻靈風暴者":[{},1],"英啟風暴者":[{},1],"鎮魂風暴者":[{},1],"薄暮風暴者":[{},1],"伊克魯斯三叉戟":[{},1],"王朝長柄戰戟":[{},1],"聖者之矛":[{},1],"岱依封長戟":[{"結晶-A級":254,"寶石-A級":100,"岱依封長戟刃部":20,"高級軟皮":52,"合成的炭焦":104,"米索莉合金":208,"恩尼亞":52,"巨匠骨架":15,"強化金屬板":208},1],"塔魯闊矛":[{"結晶-A級":193,"寶石-A級":74,"塔魯闊矛的刀身":29,"高級軟皮":37,"合成的炭焦":74,"米索莉合金":148,"恩尼亞":37,"巨匠骨架":10,"強化金屬板":148},1],"長柄戰戟":[{"結晶-B級":222,"寶石-B級":143,"長柄戰戟的刀身":25,"高級軟皮":21,"合成的炭焦":42,"米索莉合金":84,"恩尼亞":21,"巨匠骨架":8,"強化金屬板":84},1],"長槍":[{"製作卷軸(長槍100%)":1,"結晶-B級":291,"寶石-B級":98,"長槍的刀身":13,"高級軟皮":58,"合成的炭焦":116,"米索莉合金":232,"恩尼亞":58,"巨匠骨架":4},1],"巨斧":[{"製作卷軸(巨斧100%)":1,"結晶-C級":353,"寶石-B級":62,"巨斧的金屬塊":12,"高級軟皮":40,"合成的炭焦":80,"米索莉合金":160,"恩尼亞":40,"巨匠骨架":4},1],"歐西斯戰斧":[{"結晶-C級":420,"寶石-C級":248,"歐西斯戰斧的刀身":11,"高級軟皮":26,"合成的炭焦":52,"米索莉合金":104,"金屬強化劑":130},1],"蠍子":[{"結晶-C級":330,"寶石-C級":187,"蠍子的刀身":10,"高級軟皮":20,"合成的炭焦":40,"米索莉合金":80,"金屬強化劑":100},1],"黑寡婦":[{"結晶-C級":330,"寶石-C級":187,"黑寡婦的金屬塊":10,"高級軟皮":20,"合成的炭焦":40,"米索莉合金":80,"金屬強化劑":100},1],"長柄戰斧":[{"結晶-C級":300,"寶石-C級":166,"長柄戰斧的刀身":10,"高級軟皮":18,"合成的炭焦":36,"米索莉合金":72,"金屬強化劑":90},1],"貝卡合金":[{"結晶-C級":170,"寶石-C級":105,"貝卡合金的刀身":9,"高級軟皮":13,"合成的炭焦":26,"米索莉合金":52,"金屬強化劑":65},1],"大鐮刀":[{"結晶-D級":700,"寶石-C級":81,"大鐮刀的刀緣":8,"高級軟皮":10,"合成的炭焦":20,"米索莉合金":40,"金屬強化劑":50},1],"歐西斯闊矛":[{"結晶-D級":700,"寶石-C級":81,"歐西斯闊矛的刀身":8,"高級軟皮":10,"合成的炭焦":20,"米索莉合金":40,"金屬強化劑":50},1],"殺戮者":[{"結晶-D級":700,"寶石-C級":81,"殺戮者的刀身":8,"高級軟皮":10,"合成的炭焦":20,"米索莉合金":40,"金屬強化劑":50},1],"闊矛":[{"結晶-D級":550,"寶石-D級":185,"闊矛的刀身":8,"炭焦":110,"鐵":220,"高級軟皮":55},1],"翼之矛":[{"結晶-D級":430,"寶石-D級":139,"翼之矛的刀身":7,"炭焦":90,"鐵":180,"高級軟皮":45},1],"火鎚":[{"結晶-D級":430,"寶石-D級":139,"火鎚的金屬塊":7,"炭焦":90,"鐵":180,"高級軟皮":45},1],"戰鎚":[{"結晶-C級":180,"寶石-C級":105,"矮人戰鎚的金屬塊":9,"高級軟皮":19,"合成的炭焦":38,"米索莉合金":38,"金屬強化劑":76},1],"矛":[{"短矛刀身":3,"軟皮":55,"鋼鐵礦":220,"煤礦":110},1],"矮人三叉戟":[{"結晶-D級":200,"寶石-D級":57,"矮人三叉戟的刀身":5,"炭焦":40,"鐵":80,"高級軟皮":20},1],"三叉戟":[{"寶石-D級":34,"三叉戟的刀身":4,"炭焦":40,"鐵":80,"高級軟皮":20},1],"短矛":[{"短矛刀身":3,"軟皮":55,"鋼鐵礦":220,"煤礦":110},1],"異教徒之書":[{},1],"榮譽號角":[{"結晶-C級":180,"寶石-C級":105,"榮譽號角的碎片":9,"顆粒狀的骨粉":52,"合成的絞線":26,"奧里哈魯根":26,"金屬強化劑":78},1],"金剛杵":[{"金剛杵的模具":8,"結晶-D級":550,"寶石-D級":185,"絞線":130,"鐵":130,"顆粒狀的骨粉":260},1],"古代藥水":[{},1],"惡魔尖牙":[{"惡魔尖牙的尖端":7,"結晶-D級":470,"寶石-D級":153,"絞線":110,"鐵":110,"顆粒狀的骨粉":220},1],"染血十字架":[{"結晶-D級":430,"寶石-D級":139,"染血十字架的組件":7,"絞線":100,"鐵":100,"顆粒狀的骨粉":200},1],"染血卷冊":[{"結晶-D級":300,"寶石-D級":91,"染血卷冊組件":6,"絞線":70,"鐵":70,"顆粒狀的骨粉":140},1],"深淵誘惑":[{"寶石-D級":34,"深淵誘惑組件":4,"絞線":30,"鐵":30,"顆粒狀的骨粉":60},1],"狼皮甲":[{"製作卷軸(青狼皮甲100%)":1,"結晶-B級":107,"寶石-B級":22,"青狼皮甲的材料":12,"合成的絞線":35,"高級皮革":140,"金屬纖維":75,"亞索沛":35,"巨匠砧鎖":3},1],"夢魘盔甲":[{"結晶-A級":61,"寶石-A級":23,"封印的夢魘盔甲的圖樣":17,"純化的研磨劑":33,"米索莉合金":99,"亞索沛":66,"巨匠模具":20},1],"聖威金屬盔甲":[{"結晶-A級":61,"寶石-A級":23,"封印的聖威金屬盔甲的圖樣":17,"純化的研磨劑":33,"米索莉合金":99,"亞索沛":66,"巨匠模具":20},1],"塔魯金屬盔甲":[{"結晶-B級":63,"寶石-B級":156,"封印的塔魯金屬盔甲的圖樣":15,"純化的研磨劑":18,"米索莉合金":54,"亞索沛":36,"巨匠模具":8},1],"末日金屬盔甲":[{"製作卷軸(末日金屬盔甲100%)":1,"結晶-B級":136,"寶石-B級":31,"末日金屬盔甲的合金":13,"純化的研磨劑":23,"米索莉合金":69,"亞索沛":46,"巨匠模具":4},1],"全身盔甲":[{"結晶-C級":140,"寶石-C級":73,"全身盔甲的原料":11,"純化的研磨劑":12,"米索莉合金":36,"鐵匠模具":4},1],"合金盔甲":[{"結晶-C級":95,"寶石-C級":48,"合金盔甲的材料":10,"純化的研磨劑":7,"米索莉合金":21,"鐵匠模具":4},1],"大祕儀長袍":[{},1],"夢魘長袍":[{"結晶-A級":53,"寶石-A級":17,"封印的夢魘長袍的布料":17,"合成的絞線":51,"高級皮革":204,"金屬纖維":102,"亞索沛":51,"巨匠砧鎖":16},1],"聖威長袍":[{"結晶-A級":53,"寶石-A級":17,"封印的聖威長袍的布料":17,"合成的絞線":51,"高級皮革":204,"金屬纖維":102,"亞索沛":51,"巨匠砧鎖":16},1],"黑暗水晶長袍":[{"結晶-B級":49,"寶石-B級":112,"封印的黑暗水晶長袍的布料":15,"合成的絞線":35,"高級皮革":140,"金屬纖維":70,"亞索沛":35,"巨匠砧鎖":8},1],"阿巴敦長袍":[{"製作卷軸(阿巴敦長袍100%)":1,"結晶-C級":161,"寶石-B級":14,"阿巴敦長袍的布料":12,"合成的絞線":24,"高級皮革":96,"金屬纖維":48,"亞索沛":24,"巨匠砧鎖":3},1],"封印長袍":[{"結晶-C級":50,"寶石-C級":21,"封印長袍的布料":9,"合成的絞線":10,"高級皮革":40,"金屬纖維":20},1],"賢者的破衣":[{"結晶-D級":130,"寶石-D級":36,"賢者破衣的材料":8,"絞線":35,"皮革":140,"強化繩索":70},1],"艾迪奧斯脛甲":[{},1],"卡戴拉脛甲":[{},1],"煉獄脛甲":[{},1],"永生脛甲":[{},1],"薄暮脛甲":[{},1],"天命脛甲":[{},1],"王朝脛甲":[{},1],"帝國聖軍脛甲":[{},1],"黑暗水晶脛甲":[{"結晶-B級":27,"寶石-B級":59,"封印的黑暗水晶脛甲的圖樣":13,"米索莉合金":24,"亞索沛":16,"巨匠模具":3},1],"青狼脛甲":[{"製作卷軸(青狼脛甲100%)":1,"結晶-B級":49,"寶石-B級":12,"青狼脛甲的材料":13,"米索莉合金":36,"亞索沛":24,"巨匠模具":2},1],"夏隆脛甲":[{"製作卷軸(夏隆脛甲100%)":1,"結晶-C級":72,"寶石-B級":7,"夏隆脛甲的材料":12,"米索莉合金":21,"亞索沛":14,"巨匠模具":2},1],"阿巴敦脛甲":[{"製作卷軸(阿巴敦脛甲100%)":1,"結晶-C級":72,"寶石-B級":7,"阿巴敦脛甲材料":12,"米索莉合金":21,"亞索沛":14,"巨匠模具":2},1],"矮人鏈脛甲":[{"結晶-C級":25,"寶石-C級":11,"矮人鏈脛甲的原料":9,"米索莉合金":3,"鐵匠模具":2},1],"鏈脛甲":[{"結晶-D級":90,"寶石-C級":8,"鏈脛甲的原料":8,"米索莉合金":1,"鐵匠模具":2},1],"金屬脛甲":[{"結晶-D級":70,"寶石-D級":19,"金屬脛甲的原料":8,"鐵":45,"鐵鑄模":2},1],"米索莉鱗脛甲":[{"結晶-D級":60,"寶石-D級":14,"米索莉鱗脛甲材料":7,"鐵":32,"鐵鑄模":2},1],"鎖脛甲":[{"結晶-D級":60,"寶石-D級":14,"鎖脛甲材料":7,"鐵":32,"鐵鑄模":2},1],"米索莉脛甲":[{"結晶-D級":70,"寶石-C級":6,"強化米索莉脛甲的碎片":8,"高級皮革":15,"金屬纖維":15},1],"鱗脛甲":[{"結晶-D級":20,"寶石-D級":5,"鱗脛甲的原料":5,"鐵":14,"鐵鑄模":2},1],"骨片脛甲":[{"骨片脛甲的原料":3,"動物的骨頭":14,"鐵鑄模":2},1],"紅龍皮甲":[{},1],"夢魘皮甲":[{"結晶-A級":44,"寶石-A級":17,"封印的夢魘皮甲的布料":17,"合成的絞線":55,"高級皮革":220,"金屬纖維":110,"亞索沛":55,"巨匠砧鎖":16},1],"聖威皮甲":[{"結晶-A級":44,"寶石-A級":17,"封印的聖威皮甲的布料":17,"合成的絞線":55,"高級皮革":220,"金屬纖維":110,"亞索沛":55,"巨匠砧鎖":16},1],"塔魯皮甲":[{"結晶-B級":56,"寶石-B級":112,"封印的塔魯皮甲的圖樣":15,"合成的絞線":33,"高級皮革":132,"金屬纖維":66,"亞索沛":33,"巨匠砧鎖":9},1],"青狼皮甲":[{"製作卷軸(青狼皮甲100%)":1,"結晶-B級":107,"寶石-B級":22,"青狼皮甲的材料":12,"合成的絞線":35,"高級皮革":140,"金屬纖維":75,"亞索沛":35,"巨匠砧鎖":3},1],"末日皮甲":[{"製作卷軸(末日皮甲100%)":1,"結晶-B級":107,"寶石-B級":22,"末日皮甲的組件":12,"合成的絞線":35,"高級皮革":140,"金屬纖維":70,"亞索沛":35,"巨匠砧鎖":3},1],"阿巴敦皮甲":[{"製作卷軸(阿巴敦皮甲100%)":1,"結晶-C級":161,"寶石-B級":14,"阿巴敦皮甲的內襯":12,"合成的絞線":24,"高級皮革":96,"金屬纖維":48,"亞索沛":24,"巨匠砧鎖":3},1],"飛龍皮甲":[{"結晶-C級":100,"寶石-C級":53,"飛龍皮甲的材料":11,"合成的絞線":24,"高級皮革":96,"金屬纖維":48},1],"火蜥蜴皮甲":[{"結晶-D級":130,"寶石-D級":36,"火蜥蜴皮甲的組件":8,"絞線":35,"皮革":140,"強化繩索":70},1],"艾迪奧斯胸甲":[{},1],"卡戴拉胸甲":[{},1],"煉獄胸甲":[{},1],"永生胸甲":[{},1],"薄暮胸甲":[{},1],"天命胸甲":[{},1],"王朝盔甲":[{},1],"帝國聖軍胸甲":[{},1],"黑暗水晶胸甲":[{"結晶-B級":40,"寶石-B級":101,"封印的黑暗水晶胸甲的圖樣":13,"米索莉合金":42,"亞索沛":28,"巨匠模具":5},1],"青狼胸甲":[{"製作卷軸(青狼胸甲100%)":1,"結晶-B級":89,"寶石-B級":20,"青狼胸甲的碎片":13,"米索莉合金":54,"亞索沛":36,"巨匠模具":3},1],"夏隆胸甲":[{"製作卷軸(夏隆胸甲100%)":1,"結晶-C級":129,"寶石-B級":12,"夏隆胸甲的碎片":12,"米索莉合金":33,"亞索沛":22,"巨匠模具":3},1],"阿巴敦胸甲":[{"製作卷軸(阿巴敦胸甲100%)":1,"結晶-C級":129,"寶石-B級":12,"阿巴敦胸甲的碎片":12,"米索莉合金":33,"亞索沛":22,"巨匠模具":3},1],"矮人鏈甲衫":[{"結晶-C級":42,"寶石-C級":19,"矮人鏈甲衫的原料":9,"米索莉合金":5,"鐵匠模具":3},1],"鏈甲衫":[{"結晶-D級":150,"寶石-C級":14,"鏈甲衫的原料":8,"米索莉合金":1,"鐵匠模具":3},1],"半身盔甲":[{"結晶-D級":120,"寶石-D級":32,"半身盔甲的原料":8,"鐵":70,"鐵鑄模":3},1],"鎖子甲":[{"結晶-D級":90,"寶石-D級":24,"鎖子甲的原料":7,"鐵":54,"鐵鑄模":3},1],"鱗甲":[{"結晶-D級":40,"寶石-D級":9,"鱗甲的原料":5,"鐵":20,"鐵鑄模":3},1],"骨片胸甲":[{"骨片胸甲的原料":3,"鋼鐵礦":30,"鐵鑄模":3},1],"艾迪奧斯皮脛甲":[{},1],"卡戴拉皮脛甲":[{},1],"煉獄皮脛甲":[{},1],"永生皮脛甲":[{},1],"薄暮皮脛甲":[{},1],"天命皮脛甲":[{},1],"王朝皮脛甲":[{},1],"黑暗水晶皮脛甲":[{"結晶-B級":22,"寶石-B級":43,"封印的黑暗水晶皮脛甲的組件":13,"高級皮革":60,"金屬纖維":36,"亞索沛":12,"巨匠砧鎖":3},1],"夏隆皮脛甲":[{"製作卷軸(夏隆皮脛甲100%)":1,"結晶-C級":70,"寶石-B級":5,"夏隆皮脛甲的材料":12,"高級皮革":29,"金屬纖維":29,"亞索沛":29,"巨匠砧鎖":1},1],"覆殼脛甲":[{"結晶-C級":35,"寶石-C級":15,"覆殼脛甲的材料":10,"高級皮革":32,"金屬纖維":32},1],"覆皮脛甲":[{"結晶-C級":20,"寶石-C級":8,"覆皮脛甲的材料":9,"高級皮革":20,"金屬纖維":20},1],"金屬皮脛甲":[{"結晶-C級":18,"寶石-C級":7,"金屬皮脛甲的原料":9,"高級皮革":18,"金屬纖維":18},1],"強化米索莉脛甲":[{"結晶-D級":70,"寶石-C級":6,"強化米索莉脛甲的碎片":8,"高級皮革":15,"金屬纖維":15},1],"刺尾獅皮脛甲":[{"結晶-D級":45,"寶石-D級":10,"刺尾獅皮脛甲的組件":7,"皮革":45,"強化繩索":45},1],"米索莉板脛甲":[{"結晶-D級":30,"寶石-D級":6,"米索莉板脛甲的原料":6,"鐵":14,"鐵鑄模":2},1],"硬皮脛甲":[{"硬皮脛甲的材料":3,"動物的皮":55,"線":55},1],"艾迪奧斯外衣":[{},1],"卡戴拉外衣":[{},1],"煉獄外衣":[{},1],"永生外衣":[{},1],"薄暮外衣":[{},1],"天命外衣":[{},1],"王朝外衣":[{},1],"塔魯外衣":[{"結晶-B級":37,"寶石-B級":73,"封印的塔魯外衣的材料":13,"高級皮革":100,"金屬纖維":60,"亞索沛":20,"巨匠砧鎖":4},1],"青狼外衣":[{"製作卷軸(青狼外衣100%)":1,"結晶-B級":73,"寶石-B級":14,"青狼外衣的布料":13,"高級皮革":88,"金屬纖維":44,"亞索沛":44,"巨匠砧鎖":2},1],"末日外衣":[{"製作卷軸(末日外衣100%)":1,"結晶-B級":73,"寶石-B級":14,"末日外衣的圖樣":13,"高級皮革":88,"金屬纖維":44,"亞索沛":44,"巨匠砧鎖":2},1],"夏隆外衣":[{"製作卷軸(夏隆外衣100%)":1,"結晶-C級":118,"寶石-B級":9,"夏隆外衣的布料":12,"高級皮革":58,"金屬纖維":29,"亞索沛":29,"巨匠砧鎖":2},1],"神聖外衣":[{"結晶-C級":72,"寶石-C級":34,"神聖外衣的布料":11,"高級皮革":70,"金屬纖維":35},1],"惡魔外衣":[{"結晶-C級":50,"寶石-C級":22,"惡魔外衣的布料":10,"高級皮革":48,"金屬纖維":24},1],"卡勒米安外衣":[{"結晶-D級":120,"寶石-C級":10,"卡勒米安外衣的圖樣":8,"高級皮革":24,"金屬纖維":12},1],"精靈米索莉外衣":[{"精靈米索莉外衣的圖樣":7,"結晶-D級":70,"寶石-D級":17,"皮革":84,"強化繩索":42},1],"米索莉外衣":[{"結晶-D級":70,"寶石-D級":17,"米索莉外衣的布料":7,"皮革":84,"強化繩索":42},1],"純白外衣":[{"結晶-D級":28,"寶石-D級":7,"純白外衣的圖樣":5,"皮革":40,"強化繩索":20},1],"皮外衣":[{"皮外衣的圖樣":2,"動物的皮":24,"線":12},1],"外衣":[{"皮外衣的圖樣":2,"動物的皮":24,"線":12},1],"艾迪奧斯長襪":[{},1],"卡戴拉長襪":[{},1],"煉獄長襪":[{},1],"永生長襪":[{},1],"薄暮長襪":[{},1],"天命長襪":[{},1],"王朝長襪":[{},1],"塔魯長襪":[{"結晶-B級":22,"寶石-B級":43,"封印的塔魯長襪的布料":13,"高級皮革":60,"金屬纖維":36,"亞索沛":12,"巨匠砧鎖":3},1],"青狼長襪":[{"製作卷軸(青狼長襪100%)":1,"結晶-B級":47,"寶石-B級":8,"青狼長襪的圖樣":13,"高級皮革":41,"金屬纖維":41,"亞索沛":41,"巨匠砧鎖":1},1],"末日長襪":[{"製作卷軸(末日長襪100%)":1,"結晶-B級":47,"寶石-B級":8,"末日長襪的圖樣":13,"高級皮革":41,"金屬纖維":41,"亞索沛":41,"巨匠砧鎖":1},1],"夏隆長襪":[{"製作卷軸(夏隆長襪100%)":1,"結晶-C級":70,"寶石-B級":5,"夏隆長襪的布料":12,"高級皮革":29,"金屬纖維":29,"亞索沛":29,"巨匠砧鎖":1},1],"神聖長襪":[{"結晶-C級":45,"寶石-C級":20,"神聖長襪的圖樣":11,"高級皮革":42,"金屬纖維":42},1],"惡魔長襪":[{"結晶-C級":30,"寶石-C級":13,"惡魔長襪的圖樣":10,"高級皮革":30,"金屬纖維":30},1],"卡勒米安長襪":[{"結晶-D級":70,"寶石-C級":6,"卡勒米安長襪的圖樣":8,"高級皮革":15,"金屬纖維":15},1],"精靈米索莉襪":[{"精靈米索莉襪的圖樣":7,"結晶-D級":45,"寶石-D級":10,"皮革":45,"強化繩索":45},1],"米索莉長襪":[{"結晶-D級":45,"寶石-D級":10,"米索莉長襪的材料":7,"皮革":45,"強化繩索":45},1],"黑暗長襪":[{"結晶-D級":20,"寶石-D級":4,"黑暗長襪的布料":5,"皮革":20,"強化繩索":20},1],"皮長襪":[{"皮長襪的圖樣":2,"動物的皮":12,"線":12},1],"長襪":[{"皮長襪的圖樣":2,"動物的皮":12,"線":12},1],"艾迪奧斯護手":[{},1],"艾迪奧斯皮手套":[{},1],"艾迪奧斯手套":[{},1],"卡戴拉護手":[{},1],"卡戴拉皮手套":[{},1],"卡戴拉手套":[{},1],"煉獄護手":[{},1],"煉獄皮手套":[{},1],"煉獄手套":[{},1],"永生護手":[{},1],"永生皮手套":[{},1],"永生手套":[{},1],"薄暮護手":[{},1],"薄暮皮手套":[{},1],"薄暮手套":[{},1],"天命護手":[{},1],"天命皮手套":[{},1],"天命手套":[{},1],"帝國聖軍長手套":[{},1],"紅龍皮手套":[{},1],"大祕儀手套":[{},1],"夢魘長手套":[{"結晶-A級":11,"寶石-A級":3,"封印的夢魘長手套的組件":14,"高級軟皮":24,"高級皮革":40,"亞索沛":8,"巨匠砧鎖":5},1],"聖威手套":[{"結晶-A級":11,"寶石-A級":3,"封印的聖威手套的組件":14,"高級軟皮":24,"高級皮革":40,"亞索沛":8,"巨匠砧鎖":5},1],"黑暗水晶手套":[{"結晶-B級":10,"寶石-B級":21,"封印的黑暗水晶手套的組件":13,"高級軟皮":15,"高級皮革":25,"亞索沛":5,"巨匠砧鎖":2},1],"塔魯手套":[{"結晶-B級":10,"寶石-B級":21,"封印的塔魯手套的組件":13,"高級軟皮":15,"高級皮革":25,"亞索沛":5,"巨匠砧鎖":2},1],"青狼手套":[{"製作卷軸(封印的青狼手套100%)":1,"結晶-B級":15,"寶石-B級":4,"封印的青狼手套的布料":13,"高級軟皮":6,"高級皮革":48,"亞索沛":6,"巨匠砧鎖":1},1],"末日手套":[{"製作卷軸(封印的末日手套100%)":1,"結晶-B級":15,"寶石-B級":4,"封印的末日手套的碎片":13,"高級軟皮":6,"高級皮革":48,"亞索沛":6,"巨匠砧鎖":1},1],"夏隆長手套":[{"製作卷軸(封印的夏隆長手套100%)":1,"結晶-C級":33,"寶石-B級":2,"封印的夏隆長手套的碎片":12,"高級軟皮":3,"高級皮革":24,"亞索沛":3,"巨匠砧鎖":1},1],"阿巴敦手套":[{"製作卷軸(封印的阿巴敦手套100%)":1,"結晶-C級":33,"寶石-B級":2,"封印的阿巴敦手套的碎片":12,"高級軟皮":3,"高級皮革":24,"亞索沛":3,"巨匠砧鎖":1},1],"元素手套":[{"元素手套的內襯":13,"製作卷軸(元素手套100%)":1,"結晶-B級":15,"寶石-B級":4,"高級軟皮":6,"高級皮革":48,"亞索沛":6,"巨匠砧鎖":1},1],"恩寵手套":[{"恩寵手套的內襯":13,"製作卷軸(恩寵手套100%)":1,"結晶-B級":15,"寶石-B級":4,"高級軟皮":6,"高級皮革":48,"亞索沛":6,"巨匠砧鎖":1},1],"毀滅長手套":[{"毀滅長手套的布料":13,"製作卷軸(毀滅長手套100%)":1,"結晶-B級":15,"寶石-B級":4,"高級軟皮":6,"高級皮革":48,"亞索沛":6,"巨匠砧鎖":1},1],"佩勒迪亞手套":[{"佩勒迪亞手套的圖樣":13,"製作卷軸(佩勒迪亞手套100%)":1,"結晶-B級":15,"寶石-B級":4,"高級軟皮":6,"高級皮革":48,"亞索沛":6,"巨匠砧鎖":1},1],"寧靜鏈手套":[{"寧靜鏈手套的組件":12,"製作卷軸(寧靜鏈手套100%)":1,"結晶-C級":15,"寶石-B級":2,"高級軟皮":4,"高級皮革":32,"亞索沛":4,"巨匠砧鎖":1},1],"守護神手套":[{"守護神手套的組件":12,"製作卷軸(守護神手套100%)":1,"結晶-C級":15,"寶石-B級":2,"高級軟皮":4,"高級皮革":32,"亞索沛":4,"巨匠砧鎖":1},1],"死靈長手套":[{"死靈長手套的圖樣":11,"結晶-C級":24,"寶石-C級":10,"高級軟皮":3,"高級皮革":24},1],"飛龍皮手套":[{"結晶-C級":24,"寶石-C級":10,"飛龍皮手套的組件":11,"高級軟皮":3,"高級皮革":24},1],"全覆式長手套":[{"結晶-C級":24,"寶石-C級":10,"全覆式長手套的碎片":11,"高級軟皮":3,"高級皮革":24},1],"神聖手套":[{"結晶-C級":24,"寶石-C級":10,"神聖手套的圖樣":11,"高級軟皮":3,"高級皮革":24},1],"聖恩手套":[{"聖恩手套的布料":11,"結晶-C級":24,"寶石-C級":10,"高級軟皮":3,"高級皮革":24},1],"覆殼手套":[{"結晶-C級":20,"寶石-C級":7,"覆殼手套的材料":10,"高級軟皮":2,"高級皮革":18},1],"帕格立歐的手":[{"帕格立歐之手的組件":9,"結晶-C級":12,"寶石-C級":4,"高級軟皮":1,"高級皮革":10},1],"米索莉長手套":[{"結晶-C級":16,"寶石-C級":6,"米索莉長手套的組件":10,"高級軟皮":2,"高級皮革":16},1],"惡魔手套":[{"結晶-C級":16,"寶石-C級":6,"惡魔手套的布料":10,"高級軟皮":2,"高級皮革":16},1],"矮人鏈手套":[{"結晶-C級":12,"寶石-C級":4,"矮人鏈手套的組件":9,"高級軟皮":1,"高級皮革":10},1],"封印手套":[{"結晶-C級":12,"寶石-C級":4,"封印手套的圖樣":9,"高級軟皮":1,"高級皮革":10},1],"覆皮手套":[{"結晶-C級":12,"寶石-C級":4,"覆皮手套的組件":9,"高級軟皮":1,"高級皮革":10},1],"金屬皮手套":[{"結晶-C級":10,"寶石-C級":3,"金屬皮手套的組件":9,"高級軟皮":1,"高級皮革":8},1],"強化米索莉手套":[{"結晶-D級":40,"寶石-C級":3,"強化米索莉手套的組件":8,"高級軟皮":1,"高級皮革":8},1],"鏈手套":[{"結晶-D級":40,"寶石-C級":3,"鏈手套的組件":8,"高級軟皮":1,"高級皮革":8},1],"卡勒米安手套":[{"結晶-D級":40,"寶石-C級":3,"卡勒米安手套的布料":8,"高級軟皮":1,"高級皮革":8},1],"米索莉手套":[{"結晶-D級":30,"寶石-D級":6,"米索莉手套的組件":8,"皮革":32,"高級軟皮":4},1],"食人魔力量長手套":[{"結晶-D級":30,"寶石-D級":6,"食人魔力量長手套的原料":8,"皮革":32,"高級軟皮":4},1],"賢者的舊手套":[{"結晶-D級":30,"寶石-D級":6,"賢者的舊手套內襯":8,"皮革":32,"高級軟皮":4},1],"安魂長手套":[{"結晶-D級":24,"寶石-D級":5,"安魂長手套的圖樣":7,"皮革":24,"高級軟皮":3},1],"刺尾獅皮手套":[{"結晶-D級":24,"寶石-D級":5,"刺尾獅皮手套的內襯":7,"皮革":24,"高級軟皮":3},1],"鎖子甲長手套":[{"結晶-D級":24,"寶石-D級":5,"鎖子甲長手套的圖樣":7,"皮革":24,"高級軟皮":3},1],"精靈米索莉手套":[{"結晶-D級":24,"寶石-D級":5,"精靈米索莉手套的組件":7,"皮革":24,"高級軟皮":3},1],"長手套":[{"結晶-D級":24,"寶石-D級":5,"安魂長手套的圖樣":7,"皮革":24,"高級軟皮":3},1],"高級皮手套":[{"寶石-D級":1,"高級皮手套的材料":4,"皮革":8,"高級軟皮":1},1],"皮手套":[{"皮手套的材料":3,"軟皮":3,"動物的皮":24},1],"手套":[{"皮手套的材料":3,"軟皮":3,"動物的皮":24},1],"艾迪奧斯皮甲":[{},1],"卡戴拉皮甲":[{},1],"煉獄皮甲":[{},1],"永生皮甲":[{},1],"薄暮皮胸甲":[{},1],"天命皮胸甲":[{},1],"王朝皮甲":[{},1],"黑暗水晶皮甲":[{"結晶-B級":37,"寶石-B級":73,"封印的黑暗水晶皮甲的圖樣":13,"高級皮革":100,"金屬纖維":60,"亞索沛":20,"巨匠砧鎖":4},1],"夏隆皮衫":[{"製作卷軸(夏隆皮衫100%)":1,"結晶-C級":118,"寶石-B級":9,"夏隆皮衫的布料":12,"高級皮革":58,"金屬纖維":29,"亞索沛":29,"巨匠砧鎖":2},1],"覆殼皮甲":[{"結晶-C級":55,"寶石-C級":25,"覆殼皮甲的圖樣":10,"高級皮革":54,"金屬纖維":27},1],"覆皮皮甲":[{"結晶-C級":32,"寶石-C級":14,"覆皮皮甲的組件":9,"高級皮革":32,"金屬纖維":16},1],"金屬皮甲":[{"結晶-C級":30,"寶石-C級":12,"金屬皮甲的原料":9,"高級皮革":30,"金屬纖維":15},1],"刺尾獅皮襯衫":[{"結晶-D級":70,"寶石-D級":17,"刺尾獅皮襯衫的材料":7,"皮革":84,"強化繩索":42},1],"米索莉板甲":[{"結晶-D級":45,"寶石-D級":11,"米索莉板甲的原料":6,"鐵":25,"鐵鑄模":3},1],"獅皮襯衫":[{"結晶-D級":70,"寶石-D級":17,"刺尾獅皮襯衫的材料":7,"皮革":84,"強化繩索":42},1],"硬皮襯衫":[{"硬皮襯衫的圖樣":3,"動物的皮":110,"線":55},1],"皮襯衫":[{"硬皮襯衫的圖樣":3,"動物的皮":110,"線":55},1],"艾迪奧斯靴":[{},1],"艾迪奧斯皮靴":[{},1],"艾迪奧斯鞋":[{},1],"卡戴拉靴":[{},1],"卡戴拉皮靴":[{},1],"卡戴拉鞋":[{},1],"煉獄靴":[{},1],"煉獄皮靴":[{},1],"煉獄鞋":[{},1],"永生靴":[{},1],"永生皮靴":[{},1],"永生鞋":[{},1],"薄暮靴":[{},1],"薄暮皮靴":[{},1],"薄暮鞋":[{},1],"天命靴":[{},1],"天命皮靴":[{},1],"天命鞋":[{},1],"王朝長靴":[{},1],"王朝皮長靴":[{},1],"王朝鞋":[{},1],"帝國聖軍長靴":[{},1],"紅龍皮靴":[{},1],"大祕儀長靴":[{},1],"夢魘靴":[{"結晶-A級":11,"寶石-A級":3,"封印的夢魘靴的內襯":14,"高級軟皮":24,"高級皮革":40,"亞索沛":8,"巨匠砧鎖":5},1],"聖威靴":[{"結晶-A級":11,"寶石-A級":3,"封印的聖威靴的內襯":14,"高級軟皮":24,"高級皮革":40,"亞索沛":8,"巨匠砧鎖":5},1],"黑暗水晶靴":[{"結晶-B級":10,"寶石-B級":21,"封印的黑暗水晶靴的內襯":13,"高級軟皮":15,"高級皮革":25,"亞索沛":5,"巨匠砧鎖":2},1],"塔魯靴":[{"結晶-B級":10,"寶石-B級":21,"封印的塔魯靴的內襯":13,"高級軟皮":15,"高級皮革":25,"亞索沛":5,"巨匠砧鎖":2},1],"青狼長靴":[{"製作卷軸(封印的青狼長靴100%)":1,"結晶-B級":15,"寶石-B級":4,"封印的青狼長靴的圖樣":13,"高級軟皮":6,"高級皮革":48,"亞索沛":6,"巨匠砧鎖":1},1],"末日靴":[{"製作卷軸(封印的末日靴100%)":1,"結晶-B級":15,"寶石-B級":4,"封印的末日靴的碎片":13,"高級軟皮":6,"高級皮革":48,"亞索沛":6,"巨匠砧鎖":1},1],"夏隆靴":[{"製作卷軸(封印的夏隆靴100%)":1,"結晶-C級":33,"寶石-B級":2,"封印的夏隆靴的組件":12,"高級軟皮":3,"高級皮革":24,"亞索沛":3,"巨匠砧鎖":1},1],"阿巴敦靴":[{"製作卷軸(封印的阿巴敦靴100%)":1,"結晶-C級":33,"寶石-B級":2,"封印的阿巴敦靴的組件":12,"高級軟皮":3,"高級皮革":24,"亞索沛":3,"巨匠砧鎖":1},1],"佩勒迪亞靴":[{"佩勒迪亞靴的圖樣":13,"製作卷軸(佩勒迪亞靴100%)":1,"結晶-B級":15,"寶石-B級":4,"高級軟皮":6,"高級皮革":48,"亞索沛":6,"巨匠砧鎖":1},1],"元素靴":[{"元素靴的內襯":13,"製作卷軸(元素靴100%)":1,"結晶-B級":15,"寶石-B級":4,"高級軟皮":6,"高級皮革":48,"亞索沛":6,"巨匠砧鎖":1},1],"恩寵靴":[{"恩寵靴的內襯":13,"製作卷軸(恩寵靴100%)":1,"結晶-B級":15,"寶石-B級":4,"高級軟皮":6,"高級皮革":48,"亞索沛":6,"巨匠砧鎖":1},1],"寧靜靴":[{"寧靜靴的布料":12,"製作卷軸(寧靜靴100%)":1,"結晶-C級":33,"寶石-B級":2,"高級軟皮":3,"高級皮革":24,"亞索沛":3,"巨匠砧鎖":1},1],"祝福靴":[{"祝福靴的組件":12,"製作卷軸(祝福靴100%)":1,"結晶-C級":33,"寶石-B級":2,"高級軟皮":3,"高級皮革":24,"亞索沛":3,"巨匠砧鎖":1},1],"金剛石靴":[{"金剛石靴的組件":11,"結晶-C級":24,"寶石-C級":10,"高級軟皮":3,"高級皮革":24},1],"被遺忘的靴":[{"被遺忘的靴的圖樣":10,"結晶-C級":16,"寶石-C級":6,"高級軟皮":2,"高級皮革":16},1],"聖恩靴":[{"結晶-C級":24,"寶石-C級":10,"聖恩靴的布料":11,"高級軟皮":3,"高級皮革":24},1],"飛龍皮長靴":[{"結晶-C級":24,"寶石-C級":10,"飛龍皮長靴的組件":11,"高級軟皮":3,"高級皮革":24},1],"全覆式長靴":[{"結晶-C級":24,"寶石-C級":10,"全覆式長靴的碎片":11,"高級軟皮":3,"高級皮革":24},1],"覆殼長靴":[{"結晶-C級":20,"寶石-C級":7,"覆殼長靴的材料":10,"高級軟皮":2,"高級皮革":18},1],"合金靴":[{"結晶-C級":16,"寶石-C級":6,"合金靴的碎片":10,"高級軟皮":2,"高級皮革":16},1],"惡魔長靴":[{"結晶-C級":16,"寶石-C級":6,"惡魔長靴的布料":10,"高級軟皮":2,"高級皮革":16},1],"緋紅靴":[{"結晶-C級":12,"寶石-C級":4,"緋紅靴的布料":9,"高級軟皮":1,"高級皮革":10},1],"覆皮長靴":[{"結晶-C級":12,"寶石-C級":4,"覆皮長靴的內襯":9,"高級軟皮":1,"高級皮革":10},1],"強化米索莉靴":[{"結晶-D級":40,"寶石-D級":9,"強化米索莉靴的組件":8,"高級軟皮":1,"高級皮革":8},1],"鏈甲靴":[{"結晶-D級":40,"寶石-C級":3,"鏈甲靴的碎片":8,"高級軟皮":1,"高級皮革":8},1],"卡勒米安長靴":[{"結晶-D級":40,"寶石-C級":3,"卡勒米安長靴的組件":8,"高級軟皮":1,"高級皮革":8},1],"金屬皮長靴":[{"結晶-D級":40,"寶石-C級":3,"金屬皮長靴內襯":8,"高級軟皮":1,"高級皮革":8},1],"矮人鏈靴":[{"結晶-D級":40,"寶石-C級":3,"矮人鏈靴的碎片":8,"高級軟皮":1,"高級皮革":8},1],"封印長靴":[{"結晶-D級":40,"寶石-C級":3,"封印長靴的圖樣":8,"高級軟皮":1,"高級皮革":8},1],"襲擊靴":[{"結晶-D級":30,"寶石-D級":6,"襲擊靴的原料":8,"皮革":32,"高級軟皮":4},1],"火蜥蜴皮靴":[{"結晶-D級":30,"寶石-D級":6,"火蜥蜴皮靴的內襯":8,"皮革":32,"高級軟皮":4},1],"金屬靴":[{"結晶-D級":30,"寶石-D級":6,"金屬靴的組件":8,"皮革":32,"高級軟皮":4},1],"力量靴":[{"結晶-D級":24,"寶石-D級":5,"力量靴的圖樣":7,"皮革":24,"高級軟皮":3},1],"刺尾獅皮靴":[{"結晶-D級":24,"寶石-D級":5,"刺尾獅皮靴的內襯":7,"皮革":24,"高級軟皮":3},1],"鎖子長靴":[{"結晶-D級":24,"寶石-D級":5,"鎖子長靴組件":7,"皮革":24,"高級軟皮":3},1],"精靈米索莉靴":[{"結晶-D級":24,"寶石-D級":5,"精靈米索莉靴的組件":7,"皮革":24,"高級軟皮":3},1],"鋼鐵靴":[{"結晶-D級":16,"寶石-D級":3,"鋼鐵靴的組件":6,"皮革":16,"高級軟皮":2},1],"皮靴":[{"寶石-D級":1,"皮靴的材料":4,"皮革":8,"高級軟皮":1},1],"長靴":[{"長靴的材料":3,"軟皮":5,"動物的皮":40},1],"皮鞋":[{"皮鞋的材料":2,"軟皮":1,"動物的皮":8},1],"艾迪奧斯手鐲":[{},1],"卡戴拉手鐲":[{},1],"煉獄手鐲":[{},1],"永生手鐲":[{},1],"艾迪奧斯腰帶":[{},1],"卡戴拉腰帶":[{},1],"煉獄腰帶":[{},1],"永生腰帶":[{},1],"艾迪奧斯襯衫":[{},1],"卡戴拉襯衫":[{},1],"煉獄襯衫":[{},1],"永生襯衫":[{},1],"艾迪奧斯符印":[{},1],"卡戴拉符印":[{},1],"煉獄符印":[{},1],"永生符印":[{},1],"薄暮符印":[{},1],"天命符印":[{},1],"王朝符印":[{},1],"祕儀符印":[{},1],"艾迪奧斯耳環":[{},1],"卡戴拉耳環":[{},1],"煉獄耳環":[{},1],"永生耳環":[{},1],"薄暮耳環":[{},1],"天命耳環":[{},1],"王朝耳環":[{},1],"聖威耳環":[{"結晶-A級":15,"寶石-A級":5,"封印的聖威耳環的寶石":20,"純化的研磨劑":39,"金屬纖維":150,"梭芷":25,"巨匠模具":2},1],"不死鳥耳環":[{"結晶-B級":18,"寶石-B級":29,"封印的不死鳥耳環的寶石":16,"純化的研磨劑":21,"金屬纖維":35,"梭芷":7,"巨匠模具":1},1],"黑光耳環":[{"製作卷軸(黑光耳環100%)":1,"結晶-B級":25,"寶石-B級":6,"黑光耳環的碎片":13,"純化的研磨劑":13,"金屬纖維":65,"梭芷":13,"巨匠模具":1},1],"金剛石耳環":[{"製作卷軸(金剛石耳環100%)":1,"結晶-C級":35,"寶石-B級":4,"金剛石耳環的寶石":12,"純化的研磨劑":8,"金屬纖維":40,"梭芷":8,"巨匠模具":1},1],"娜仙耳環":[{"結晶-C級":28,"寶石-C級":12,"娜仙耳環的寶石":11,"純化的研磨劑":9,"鐵匠模具":1,"金屬纖維":45},1],"封印耳環":[{"結晶-C級":22,"寶石-C級":8,"封印耳環的寶石":10,"純化的研磨劑":4,"鐵匠模具":1,"金屬纖維":20},1],"守護耳環":[{"結晶-C級":14,"寶石-C級":5,"守護耳環的寶石":9,"純化的研磨劑":1,"鐵匠模具":1,"金屬纖維":5},1],"月長石耳環":[{"結晶-D級":30,"寶石-C級":4,"月長石耳環的金屬線":8,"純化的研磨劑":1,"鐵匠模具":1,"金屬纖維":5},1],"瑪瑙獸眼耳環":[{"結晶-D級":40,"寶石-D級":8,"瑪瑙獸眼耳環的寶石":8,"研磨劑":18,"強化繩索":90,"銀鑄模":1},1],"精靈耳環":[{"結晶-D級":30,"寶石-D級":6,"精靈耳環的珠子":7,"研磨劑":12,"強化繩索":60,"銀鑄模":1},1],"虎眼耳環":[{"結晶-D級":22,"寶石-D級":4,"虎眼耳環的石頭":6,"研磨劑":6,"強化繩索":30,"銀鑄模":1},1],"艾迪奧斯戒指":[{},1],"卡戴拉戒指":[{},1],"煉獄戒指":[{},1],"永生戒指":[{},1],"薄暮戒指":[{},1],"天命戒指":[{},1],"王朝戒指":[{},1],"聖威戒指":[{"結晶-A級":12,"寶石-A級":3,"封印的聖威戒指的寶石":19,"純化的研磨劑":27,"鐵匠模具":3,"金屬纖維":115,"梭芷":18},1],"不死鳥戒指":[{"結晶-B級":11,"寶石-B級":18,"封印的不死鳥戒指的寶石":15,"純化的研磨劑":18,"鐵匠模具":2,"金屬纖維":30,"梭芷":6},1],"黑光戒指":[{"製作卷軸(黑光戒指100%)":1,"結晶-B級":18,"寶石-B級":4,"黑光戒指的金屬線":13,"純化的研磨劑":10,"鐵匠模具":1,"金屬纖維":50,"梭芷":10},1],"金剛石戒指":[{"製作卷軸(金剛石戒指100%)":1,"結晶-C級":32,"寶石-B級":2,"金剛石戒指的金屬線":12,"純化的研磨劑":6,"鐵匠模具":1,"金屬纖維":30,"梭芷":6},1],"賢者戒指":[{"賢者戒指的寶石":13,"製作卷軸((賢者戒指100%)":1,"結晶-B級":18,"寶石-B級":4,"純化的研磨劑":10,"鐵匠模具":1,"金屬纖維":50,"梭芷":10},1],"封印戒指":[{"結晶-C級":20,"寶石-C級":7,"封印戒指的寶石":11,"銀鑄模":1,"純化的研磨劑":8,"金屬纖維":40},1],"永命戒指":[{"結晶-C級":12,"寶石-C級":5,"永命戒指的寶石":10,"銀鑄模":1,"純化的研磨劑":6,"金屬纖維":30},1],"守護戒指":[{"結晶-C級":10,"寶石-C級":3,"守護戒指的寶石":9,"銀鑄模":1,"純化的研磨劑":3,"金屬纖維":15},1],"水石戒指":[{"結晶-D級":25,"寶石-C級":2,"水石戒指的金屬線":8,"銀鑄模":1,"純化的研磨劑":3,"金屬纖維":15},1],"米索莉戒指":[{"結晶-D級":25,"寶石-D級":5,"米索莉戒指的金屬線":8,"研磨劑":10,"強化繩索":50,"銀鑄模":1},1],"精靈戒指":[{"結晶-D級":20,"寶石-D級":4,"精靈戒指的組件":7,"研磨劑":6,"強化繩索":30,"銀鑄模":1},1],"艾迪奧斯頭盔":[{},1],"艾迪奧斯皮頭盔":[{},1],"艾迪奧斯頭箍":[{},1],"卡戴拉頭盔":[{},1],"卡戴拉皮頭盔":[{},1],"卡戴拉頭箍":[{},1],"煉獄頭盔":[{},1],"煉獄皮頭盔":[{},1],"煉獄頭箍":[{},1],"永生頭盔":[{},1],"永生皮頭盔":[{},1],"永生頭箍":[{},1],"薄暮頭盔":[{},1],"薄暮皮頭盔":[{},1],"薄暮頭箍":[{},1],"天命頭盔":[{},1],"天命皮頭盔":[{},1],"天命頭箍":[{},1],"王朝頭盔":[{},1],"王朝皮頭盔":[{},1],"王朝頭箍":[{},1],"帝國聖軍頭盔":[{},1],"紅龍皮盔":[{},1],"大祕儀頭箍":[{},1],"夢魘頭盔":[{"結晶-A級":15,"寶石-A級":5,"封印的夢魘頭盔的組件":14,"高級皮革":80,"亞索沛":8,"巨匠模具":4},1],"聖威頭箍":[{"結晶-A級":15,"寶石-A級":5,"封印的聖威頭箍的組件":14,"高級皮革":80,"亞索沛":8,"巨匠模具":4},1],"黑暗水晶頭盔":[{"結晶-B級":19,"寶石-B級":33,"封印的黑暗水晶頭盔的組件":13,"高級皮革":40,"亞索沛":4,"巨匠模具":2},1],"塔魯帽":[{"結晶-B級":19,"寶石-B級":33,"封印的塔魯帽的組件":13,"高級皮革":40,"亞索沛":4,"巨匠模具":2},1],"青狼頭盔":[{"製作卷軸(青狼頭盔100%)":1,"結晶-B級":39,"寶石-B級":7,"青狼頭盔的組件":13,"高級皮革":50,"亞索沛":5,"巨匠模具":1},1],"末日頭盔":[{"製作卷軸(末日頭盔100%)":1,"結晶-B級":39,"寶石-B級":7,"末日頭盔的圖樣":13,"高級皮革":50,"亞索沛":5,"巨匠模具":1},1],"夏隆頭盔":[{"製作卷軸(夏隆頭盔100%)":1,"結晶-C級":41,"寶石-B級":4,"夏隆頭盔的組件":12,"高級皮革":40,"亞索沛":4,"巨匠模具":1},1],"阿巴敦頭箍":[{"製作卷軸(阿巴敦頭箍100%)":1,"結晶-C級":41,"寶石-B級":4,"阿巴敦頭箍的圖樣":12,"高級皮革":40,"亞索沛":4,"巨匠模具":1},1],"米索莉頭盔":[{"米索莉頭盔的圖樣":11,"結晶-C級":36,"寶石-C級":15,"鐵匠模具":1,"高級皮革":26},1],"全覆式頭盔":[{"結晶-C級":36,"寶石-C級":15,"全覆式頭盔的組件":11,"鐵匠模具":1,"高級皮革":26},1],"合金頭盔":[{"結晶-C級":25,"寶石-C級":10,"合金頭盔的組件":10,"鐵匠模具":1,"高級皮革":14},1],"閃耀頭箍":[{"結晶-C級":25,"寶石-C級":10,"閃耀頭箍的圖樣":10,"鐵匠模具":1,"高級皮革":14},1],"巨型頭盔":[{"結晶-C級":16,"寶石-C級":6,"巨型頭盔的原料":9,"鐵匠模具":1,"高級皮革":6},1],"金屬頭盔":[{"結晶-C級":14,"寶石-C級":5,"金屬頭盔的原料":9,"鐵匠模具":1,"高級皮革":3},1],"鏈頭巾":[{"結晶-D級":60,"寶石-C級":5,"鏈頭巾的圖樣":8,"鐵匠模具":1,"高級皮革":2},1],"鎖鏈頭盔":[{"結晶-D級":45,"寶石-D級":10,"鎖鏈頭盔的組件":8,"皮革":60,"鐵鑄模":1},1],"金屬板頭盔":[{"結晶-D級":45,"寶石-D級":10,"金屬板頭盔的組件":8,"皮革":60,"鐵鑄模":1},1],"鎖子頭盔":[{"結晶-D級":35,"寶石-D級":8,"鎖子頭盔的組件":7,"皮革":20,"鐵鑄模":1},1],"頭盔":[{"皮頭盔的組件":3,"軟皮":15,"動物的皮":12},1],"骨頭盔":[{"寶石-D級":2,"骨頭盔的組件":4,"皮革":15,"鐵鑄模":1},1],"皮頭盔":[{"皮頭盔的組件":3,"軟皮":15,"動物的皮":12},1],"艾迪奧斯盾":[{},1],"卡戴拉盾":[{},1],"煉獄盾":[{},1],"永生盾":[{},1],"薄暮衛盾":[{},1],"天命盾":[{},1],"王朝盾":[{},1],"帝國聖軍盾":[{},1],"夢魘盾":[{"結晶-A級":12,"寶石-A級":3,"封印的夢魘盾碎片":14,"合成的炭焦":7,"米索莉合金":21,"高級皮革":7,"亞索沛":7,"巨匠砧鎖":5},1],"黑暗水晶盾":[{"結晶-B級":9,"寶石-B級":22,"封印的黑暗水晶盾碎片":13,"合成的炭焦":4,"米索莉合金":12,"高級皮革":4,"亞索沛":4,"巨匠砧鎖":2},1],"末日盾":[{"製作卷軸(末日盾100%)":1,"結晶-B級":20,"寶石-B級":4,"末日盾的碎片":13,"合成的炭焦":3,"米索莉合金":9,"高級皮革":3,"亞索沛":3,"巨匠砧鎖":1},1],"夏隆盾":[{"製作卷軸(夏隆盾100%)":1,"結晶-C級":16,"寶石-B級":3,"夏隆盾的碎片":12,"合成的炭焦":4,"米索莉合金":12,"高級皮革":4,"亞索沛":4,"巨匠砧鎖":1},1],"阿巴敦盾":[{"製作卷軸(阿巴敦盾100%)":1,"結晶-C級":16,"寶石-B級":3,"阿巴敦盾的破片":12,"合成的炭焦":4,"米索莉合金":12,"高級皮革":4,"亞索沛":4,"巨匠砧鎖":1},1],"全覆式盾":[{"結晶-C級":25,"寶石-C級":10,"全覆式盾的碎片":11,"合成的炭焦":3,"米索莉合金":9,"高級皮革":3},1],"塔盾":[{"結晶-D級":40,"寶石-C級":3,"厄達拉克塔盾的原料":8,"合成的炭焦":1,"米索莉合金":3,"高級皮革":1},1],"合金盾":[{"結晶-C級":17,"寶石-C級":7,"合金盾的碎片":10,"合成的炭焦":2,"米索莉合金":6,"高級皮革":2},1],"騎士盾":[{"結晶-C級":12,"寶石-C級":4,"騎士盾的材料":9,"合成的炭焦":1,"米索莉合金":4,"高級皮革":1},1],"矮人鏈盾":[{"結晶-C級":12,"寶石-C級":4,"矮人鏈盾的碎片":9,"合成的炭焦":1,"米索莉合金":3,"高級皮革":1},1],"厄達拉克塔盾":[{"結晶-D級":40,"寶石-C級":3,"厄達拉克塔盾的原料":8,"合成的炭焦":1,"米索莉合金":3,"高級皮革":1},1],"鏈盾":[{"結晶-D級":40,"寶石-C級":3,"鏈盾的碎片":8,"合成的炭焦":1,"米索莉合金":3,"高級皮革":1},1],"方盾":[{"結晶-D級":32,"寶石-D級":7,"方盾的原料":8,"炭焦":5,"鐵":15,"皮革":5},1],"金屬盾":[{"結晶-D級":32,"寶石-D級":7,"金屬盾的碎片":8,"炭焦":5,"鐵":15,"皮革":5},1],"鳶形盾":[{"結晶-D級":24,"寶石-D級":5,"鳶形盾的原料":7,"炭焦":4,"鐵":12,"皮革":4},1],"鎖子盾":[{"結晶-D級":24,"寶石-D級":5,"鎖子盾的碎片":7,"炭焦":4,"鐵":12,"皮革":4},1],"艾迪奧斯項鍊":[{},1],"卡戴拉項鍊":[{},1],"煉獄項鍊":[{},1],"永生項鍊":[{},1],"薄暮項鍊":[{},1],"天命項鍊":[{},1],"王朝項鍊":[{},1],"聖威項鍊":[{"結晶-A級":17,"寶石-A級":6,"封印的聖威項鍊的珠子":17,"純化的研磨劑":60,"金屬纖維":200,"梭芷":30,"巨匠模具":3},1],"不死鳥項鍊":[{"結晶-B級":23,"寶石-B級":12,"封印的不死鳥項鍊的珠子":17,"純化的研磨劑":33,"金屬纖維":100,"梭芷":20,"巨匠模具":2},1],"黑光項鍊":[{"製作卷軸(黑光項鍊100%)":1,"結晶-B級":37,"寶石-B級":8,"黑光項鍊的珠子":13,"純化的研磨劑":11,"合成的絞線":55,"梭芷":11,"巨匠模具":1},1],"金剛石項鍊":[{"製作卷軸(金剛石項鍊100%)":1,"結晶-C級":58,"寶石-B級":5,"金剛石項鍊的鍊子":12,"純化的研磨劑":7,"合成的絞線":35,"梭芷":7,"巨匠模具":1},1],"賢者項鍊":[{"賢者項鍊的鍊子":13,"製作卷軸(賢者項鍊100%)":1,"結晶-B級":37,"寶石-B級":8,"純化的研磨劑":11,"合成的絞線":55,"梭芷":11,"巨匠模具":1},1],"封印項鍊":[{"結晶-C級":38,"寶石-C級":16,"封印項鍊的鍊子":11,"純化的研磨劑":7,"合成的絞線":35,"鐵匠模具":1},1],"人魚之淚":[{"結晶-C級":26,"寶石-C級":11,"人魚之淚的淚珠":10,"純化的研磨劑":4,"合成的絞線":20,"鐵匠模具":1},1],"守護項鍊":[{"結晶-C級":16,"寶石-C級":7,"守護項鍊的寶石":9,"純化的研磨劑":2,"合成的絞線":10,"鐵匠模具":1},1],"水石項鍊":[{"結晶-D級":65,"寶石-C級":5,"水石項鍊的鍊子":8,"純化的研磨劑":1,"合成的絞線":5,"鐵匠模具":1},1],"黑暗項鍊":[{"結晶-D級":50,"寶石-D級":12,"黑暗項鍊的寶石":8,"研磨劑":18,"絞線":90,"銀鑄模":1},1],"精靈項鍊":[{"結晶-D級":38,"寶石-D級":9,"精靈項鍊的珠子":7,"研磨劑":14,"絞線":70,"銀鑄模":1},1],"魔力項鍊":[{"結晶-D級":18,"寶石-D級":3,"魔力項鍊的鍊子":5,"研磨劑":3,"絞線":15,"銀鑄模":1},1],"奉獻項鍊":[{"寶石-D級":2,"奉獻項鍊的鍊子":4,"研磨劑":3,"絞線":15,"銀鑄模":1},1],"藍鑽項鍊":[{"藍鑽項鍊的鍊子":3,"樹枝":80,"研磨劑":16},1],"智慧項鍊":[{"智慧項鍊的鍊子":3,"樹枝":50,"研磨劑":10},1],"幻滅項鍊":[{"幻滅項鍊的鍊子":2,"樹枝":20,"研磨劑":4},1],"結晶-A級":[{},1],"寶石-A級":[{},1],"貝希莫斯巨叉碎片":[{},1],"高級軟皮":[{"軟皮":3,"顆粒狀的骨粉":1},1],"合成的炭焦":[{"奧里哈魯根原石":1,"炭焦":3},1],"米索莉合金":[{"米索莉原石":1,"鐵":2,"純化的研磨劑":1},1],"恩尼亞":[{},1],"巨匠骨架":[{"純化的研磨劑":10,"鑄模的潤滑劑":10,"鑄模的強化劑":10},1],"強化金屬板":[{"米索莉原石":5,"金屬絲":5},1],"末日毀滅者金屬塊":[{},1],"結晶-B級":[{},1],"寶石-B級":[{},1],"破壞者巨鎚組件":[{},1],"結晶-D級":[{},1],"寶石-D級":[{},1],"下巨人之鎚組件":[{},1],"炭焦":[{"煤礦":3,"木炭":3},1],"鐵":[{"研磨劑":5,"鋼鐵礦":5},1],"那卡風暴碎片":[{},1],"刀匠鑄模":[{"工匠模具":2,"鑄模的強化劑":20,"恩尼亞":5},1],"魂體分離器的刀身":[{},1],"血腥之蘭的刀身":[{},1],"製作卷軸(惡魔短劍100%)":[{},1],"惡魔短劍的刀身":[{},1],"製作卷軸(波形刃100%)":[{},1],"結晶-C級":[{},1],"波形刃的刀身":[{},1],"製作卷軸(地獄刀100%)":[{},1],"地獄刀的刀身":[{},1],"寶石-C級":[{},1],"水晶匕首的刀身":[{},1],"工匠模具":[{"金剛石塊":10,"鐵鑄模":1,"純化的研磨劑":5},1],"金屬強化劑":[{"樹枝":10,"研磨劑":10,"鋼鐵礦":10},1],"優雅匕首的刀身":[{},1],"黑暗狂嘯者的刀身":[{},1],"袖珍刀的刀身":[{},1],"魔炎匕首的刀身":[{},1],"受詛咒匕首的刀身":[{},1],"狼之針的刀緣":[{},1],"黑暗精靈匕首的刀緣":[{},1],"米索莉匕首的刀身":[{},1],"鐵鑄模":[{"鋼鐵礦":5,"煤礦":5,"絞線":5},1],"突刺刀的刀緣":[{},1],"受詛咒的突刺刀刀緣":[{},1],"森林神之刀的刀身":[{},1],"刺客刀的刀身":[{},1],"碎劍者的劍身":[{},1],"鋼鐵礦":[{},1],"煤礦":[{},1],"短刀的刀身":[{},1],"卡布里歐之手金屬塊":[{},1],"顆粒狀的骨粉":[{"動物的骨頭":10},1],"合成的絞線":[{"線":5,"絞線":5},1],"奧里哈魯根":[{"銀塊":12,"奧里哈魯根原石":4,"合成的炭焦":1},1],"火龍之首組件":[{},1],"英魂之眼組件":[{},1],"永恆手杖的金屬塊":[{},1],"自然之棍的金屬塊":[{},1],"底獄之鎚的金屬塊":[{},1],"信仰手杖的柄":[{},1],"生命手杖的柄":[{},1],"絞線":[{"樹枝":5},1],"審判之鎚的刀身":[{},1],"貝拉凱爾聖斧碎片":[{},1],"樂園的金屬塊":[{},1],"流星雨的金屬塊":[{},1],"製作卷軸(亡者榮譽100%)":[{},1],"亡者榮譽的石材":[{},1],"製作卷軸(工藝戰斧100%)":[{},1],"工藝戰斧的刀身":[{},1],"製作卷軸(巨大戰斧100%)":[{},1],"巨大戰斧的金屬塊":[{},1],"夜叉釘鎚的金屬塊":[{},1],"巨戰斧的刀身":[{},1],"夢想斧的刀身":[{},1],"矮人戰鎚的金屬塊":[{},1],"重鎚的金屬塊":[{},1],"戰斧的金屬塊":[{},1],"戰錐的金屬塊":[{},1],"顱骨雕刻者的金屬塊":[{},1],"碎骨者的金屬塊":[{},1],"流星鎚的金屬塊":[{},1],"塔巴曲刃斧的金屬塊":[{},1],"頭顱破壞者的金屬塊":[{},1],"巨大骨棒的金屬塊":[{},1],"山羊頭之杖的金屬塊":[{},1],"狼牙棒的金屬塊":[{},1],"鋼鎚的金屬塊":[{},1],"軟皮":[{},1],"大鐮刀的刀緣":[{},1],"阿吐巴釘鎚的金屬塊":[{},1],"伊波斯巨劍劍身":[{},1],"斬龍刀的刀身":[{},1],"煉獄之主刃部":[{},1],"製作卷軸(巨劍100%)":[{},1],"巨劍的刀身":[{},1],"狂戰士之刃的刀身":[{},1],"焰形劍的劍身":[{},1],"雙刃大砍刀的刀身":[{},1],"重型劍的刀身":[{},1],"鋼劍劍身":[{},1],"雙手劍的劍身":[{},1],"刺擊刀的刀身":[{},1],"緹米絲之舌碎片":[{},1],"奇蹟劍的刀身":[{},1],"元素劍的刀身":[{},1],"製作卷軸(聖堂之劍100%)":[{},1],"聖堂之劍的刀身":[{},1],"何門奎思之劍的劍身":[{},1],"死息之劍的劍身":[{},1],"黑暗軍刀的刀身":[{},1],"塔魯刀的刀身":[{},1],"製作卷軸(大馬士革刀100%)":[{},1],"大馬士革刀的劍身":[{},1],"製作卷軸(柯貝克劍100%)":[{},1],"柯貝克劍的劍身":[{},1],"瑟魯基長劍的劍身":[{},1],"卡里埔士劍的劍身":[{},1],"迷惑之劍的劍身":[{},1],"大和劍的劍身":[{},1],"極限之劍的劍身":[{},1],"夢魘劍的劍身":[{},1],"彎刀的刀身":[{},1],"武士刀的刀身":[{},1],"靈魂之劍的劍身":[{},1],"襲擊劍的劍身":[{},1],"暴風之劍的劍身":[{},1],"精靈長劍的劍身":[{},1],"革命劍的劍身":[{},1],"椎骨之劍的劍身":[{},1],"軍刀的刀身":[{},1],"反射劍的劍身":[{},1],"寬劍的劍身":[{},1],"惡魔結晶碎片":[{},1],"世界樹樹枝的金屬塊":[{},1],"帕黎恩魔杖的金屬塊":[{},1],"製作卷軸(邪靈魔杖100%)":[{},1],"邪靈魔杖的金屬塊":[{},1],"製作卷軸(精靈魔杖100%)":[{},1],"精靈魔杖的金屬塊":[{},1],"亡者魔杖的金屬塊":[{},1],"食屍鬼魔杖的金屬塊":[{},1],"惡魔魔杖的金屬塊":[{},1],"帕格立歐之斧的刀身":[{},1],"佩勒迪亞魔杖的金屬塊":[{},1],"地獄魔杖的金屬塊":[{},1],"帕格立歐之鎚的金屬塊":[{},1],"賢者魔杖的金屬塊":[{},1],"受詛咒魔杖的金屬塊":[{},1],"巨大末日鎚的金屬塊":[{},1],"水晶魔杖的金屬塊":[{},1],"巨大末日斧的刀身":[{},1],"阿吐巴鎚的金屬塊":[{},1],"魂靈魔杖的金屬塊":[{},1],"法咒魔杖的金屬塊":[{},1],"柏木魔杖的金屬塊":[{},1],"樹枝":[{},1],"動物的骨頭":[{},1],"柳木魔杖的金屬塊":[{},1],"夏伊德獵弓柄":[{},1],"靈魂弓的柄":[{},1],"顱之弓的柄":[{},1],"製作卷軸(冒險弓100%)":[{},1],"冒險弓的柄":[{},1],"製作卷軸(黑暗精靈長弓100%)":[{},1],"黑暗精靈長弓的柄":[{},1],"卓越弓的柄":[{},1],"阿卡特長弓的柄":[{},1],"元素弓的柄":[{},1],"高級精靈弓的金屬塊":[{},1],"冰晶弓的柄":[{},1],"風暴弓的柄":[{},1],"強化長弓的柄":[{},1],"腰弩的柄":[{},1],"精靈弓的柄":[{},1],"合金弓的柄":[{},1],"森林弓的柄":[{},1],"弓的金屬塊":[{},1],"索貝克颶風刀緣":[{},1],"龍牙的刀身":[{},1],"血旋風的刀身":[{},1],"製作卷軸(博利恩拳套100%)":[{},1],"博利恩拳套的刃部":[{},1],"巨型帕塔拳刃的刀身":[{},1],"製作卷軸(阿斯拉爪100%)":[{},1],"阿斯拉爪的刀身":[{},1],"拳刃的刀身":[{},1],"關節拳的刃":[{},1],"圓月輪的刀緣":[{},1],"波浪刀的刀緣":[{},1],"拳套刀的刀緣":[{},1],"岱依封長戟刃部":[{},1],"塔魯闊矛的刀身":[{},1],"長柄戰戟的刀身":[{},1],"製作卷軸(長槍100%)":[{},1],"長槍的刀身":[{},1],"製作卷軸(巨斧100%)":[{},1],"巨斧的金屬塊":[{},1],"歐西斯戰斧的刀身":[{},1],"蠍子的刀身":[{},1],"黑寡婦的金屬塊":[{},1],"長柄戰斧的刀身":[{},1],"貝卡合金的刀身":[{},1],"歐西斯闊矛的刀身":[{},1],"殺戮者的刀身":[{},1],"闊矛的刀身":[{},1],"翼之矛的刀身":[{},1],"火鎚的金屬塊":[{},1],"短矛刀身":[{},1],"矮人三叉戟的刀身":[{},1],"三叉戟的刀身":[{},1],"榮譽號角的碎片":[{},1],"金剛杵的模具":[{},1],"惡魔尖牙的尖端":[{},1],"染血十字架的組件":[{},1],"染血卷冊組件":[{},1],"深淵誘惑組件":[{},1],"製作卷軸(青狼皮甲100%)":[{},1],"青狼皮甲的材料":[{},1],"高級皮革":[{"煤礦":4,"皮革":4,"強化繩索":4},1],"金屬纖維":[{"銀塊":15,"強化繩索":20},20],"亞索沛":[{},1],"巨匠砧鎖":[{"合成的炭焦":4,"鑄模的黏劑":4,"鑄模的潤滑劑":4},1],"封印的夢魘盔甲的圖樣":[{},1],"純化的研磨劑":[{"研磨劑":3,"純石":1,"顆粒狀的骨粉":3},1],"巨匠模具":[{"鐵匠模具":1,"鑄模的黏劑":10,"亞索沛":5},1],"封印的聖威金屬盔甲的圖樣":[{},1],"封印的塔魯金屬盔甲的圖樣":[{},1],"製作卷軸(末日金屬盔甲100%)":[{},1],"末日金屬盔甲的合金":[{},1],"全身盔甲的原料":[{},1],"鐵匠模具":[{"米索莉原石":10,"銀鑄模":1,"純化的研磨劑":5},1],"合金盔甲的材料":[{},1],"封印的夢魘長袍的布料":[{},1],"封印的聖威長袍的布料":[{},1],"封印的黑暗水晶長袍的布料":[{},1],"製作卷軸(阿巴敦長袍100%)":[{},1],"阿巴敦長袍的布料":[{},1],"封印長袍的布料":[{},1],"賢者破衣的材料":[{},1],"皮革":[{"動物的皮":6},1],"強化繩索":[{"線":25,"鐵":2},20],"封印的黑暗水晶脛甲的圖樣":[{},1],"製作卷軸(青狼脛甲100%)":[{},1],"青狼脛甲的材料":[{},1],"製作卷軸(夏隆脛甲100%)":[{},1],"夏隆脛甲的材料":[{},1],"製作卷軸(阿巴敦脛甲100%)":[{},1],"阿巴敦脛甲材料":[{},1],"矮人鏈脛甲的原料":[{},1],"鏈脛甲的原料":[{},1],"金屬脛甲的原料":[{},1],"米索莉鱗脛甲材料":[{},1],"鎖脛甲材料":[{},1],"強化米索莉脛甲的碎片":[{},1],"鱗脛甲的原料":[{},1],"骨片脛甲的原料":[{},1],"封印的夢魘皮甲的布料":[{},1],"封印的聖威皮甲的布料":[{},1],"封印的塔魯皮甲的圖樣":[{},1],"製作卷軸(末日皮甲100%)":[{},1],"末日皮甲的組件":[{},1],"製作卷軸(阿巴敦皮甲100%)":[{},1],"阿巴敦皮甲的內襯":[{},1],"飛龍皮甲的材料":[{},1],"火蜥蜴皮甲的組件":[{},1],"封印的黑暗水晶胸甲的圖樣":[{},1],"製作卷軸(青狼胸甲100%)":[{},1],"青狼胸甲的碎片":[{},1],"製作卷軸(夏隆胸甲100%)":[{},1],"夏隆胸甲的碎片":[{},1],"製作卷軸(阿巴敦胸甲100%)":[{},1],"阿巴敦胸甲的碎片":[{},1],"矮人鏈甲衫的原料":[{},1],"鏈甲衫的原料":[{},1],"半身盔甲的原料":[{},1],"鎖子甲的原料":[{},1],"鱗甲的原料":[{},1],"骨片胸甲的原料":[{},1],"封印的黑暗水晶皮脛甲的組件":[{},1],"製作卷軸(夏隆皮脛甲100%)":[{},1],"夏隆皮脛甲的材料":[{},1],"覆殼脛甲的材料":[{},1],"覆皮脛甲的材料":[{},1],"金屬皮脛甲的原料":[{},1],"刺尾獅皮脛甲的組件":[{},1],"米索莉板脛甲的原料":[{},1],"硬皮脛甲的材料":[{},1],"動物的皮":[{},1],"線":[{},1],"封印的塔魯外衣的材料":[{},1],"製作卷軸(青狼外衣100%)":[{},1],"青狼外衣的布料":[{},1],"製作卷軸(末日外衣100%)":[{},1],"末日外衣的圖樣":[{},1],"製作卷軸(夏隆外衣100%)":[{},1],"夏隆外衣的布料":[{},1],"神聖外衣的布料":[{},1],"惡魔外衣的布料":[{},1],"卡勒米安外衣的圖樣":[{},1],"精靈米索莉外衣的圖樣":[{},1],"米索莉外衣的布料":[{},1],"純白外衣的圖樣":[{},1],"皮外衣的圖樣":[{},1],"封印的塔魯長襪的布料":[{},1],"製作卷軸(青狼長襪100%)":[{},1],"青狼長襪的圖樣":[{},1],"製作卷軸(末日長襪100%)":[{},1],"末日長襪的圖樣":[{},1],"製作卷軸(夏隆長襪100%)":[{},1],"夏隆長襪的布料":[{},1],"神聖長襪的圖樣":[{},1],"惡魔長襪的圖樣":[{},1],"卡勒米安長襪的圖樣":[{},1],"精靈米索莉襪的圖樣":[{},1],"米索莉長襪的材料":[{},1],"黑暗長襪的布料":[{},1],"皮長襪的圖樣":[{},1],"封印的夢魘長手套的組件":[{},1],"封印的聖威手套的組件":[{},1],"封印的黑暗水晶手套的組件":[{},1],"封印的塔魯手套的組件":[{},1],"製作卷軸(封印的青狼手套100%)":[{},1],"封印的青狼手套的布料":[{},1],"製作卷軸(封印的末日手套100%)":[{},1],"封印的末日手套的碎片":[{},1],"製作卷軸(封印的夏隆長手套100%)":[{},1],"封印的夏隆長手套的碎片":[{},1],"製作卷軸(封印的阿巴敦手套100%)":[{},1],"封印的阿巴敦手套的碎片":[{},1],"元素手套的內襯":[{},1],"製作卷軸(元素手套100%)":[{},1],"恩寵手套的內襯":[{},1],"製作卷軸(恩寵手套100%)":[{},1],"毀滅長手套的布料":[{},1],"製作卷軸(毀滅長手套100%)":[{},1],"佩勒迪亞手套的圖樣":[{},1],"製作卷軸(佩勒迪亞手套100%)":[{},1],"寧靜鏈手套的組件":[{},1],"製作卷軸(寧靜鏈手套100%)":[{},1],"守護神手套的組件":[{},1],"製作卷軸(守護神手套100%)":[{},1],"死靈長手套的圖樣":[{},1],"飛龍皮手套的組件":[{},1],"全覆式長手套的碎片":[{},1],"神聖手套的圖樣":[{},1],"聖恩手套的布料":[{},1],"覆殼手套的材料":[{},1],"帕格立歐之手的組件":[{},1],"米索莉長手套的組件":[{},1],"惡魔手套的布料":[{},1],"矮人鏈手套的組件":[{},1],"封印手套的圖樣":[{},1],"覆皮手套的組件":[{},1],"金屬皮手套的組件":[{},1],"強化米索莉手套的組件":[{},1],"鏈手套的組件":[{},1],"卡勒米安手套的布料":[{},1],"米索莉手套的組件":[{},1],"食人魔力量長手套的原料":[{},1],"賢者的舊手套內襯":[{},1],"安魂長手套的圖樣":[{},1],"刺尾獅皮手套的內襯":[{},1],"鎖子甲長手套的圖樣":[{},1],"精靈米索莉手套的組件":[{},1],"高級皮手套的材料":[{},1],"皮手套的材料":[{},1],"封印的黑暗水晶皮甲的圖樣":[{},1],"製作卷軸(夏隆皮衫100%)":[{},1],"夏隆皮衫的布料":[{},1],"覆殼皮甲的圖樣":[{},1],"覆皮皮甲的組件":[{},1],"金屬皮甲的原料":[{},1],"刺尾獅皮襯衫的材料":[{},1],"米索莉板甲的原料":[{},1],"硬皮襯衫的圖樣":[{},1],"封印的夢魘靴的內襯":[{},1],"封印的聖威靴的內襯":[{},1],"封印的黑暗水晶靴的內襯":[{},1],"封印的塔魯靴的內襯":[{},1],"製作卷軸(封印的青狼長靴100%)":[{},1],"封印的青狼長靴的圖樣":[{},1],"製作卷軸(封印的末日靴100%)":[{},1],"封印的末日靴的碎片":[{},1],"製作卷軸(封印的夏隆靴100%)":[{},1],"封印的夏隆靴的組件":[{},1],"製作卷軸(封印的阿巴敦靴100%)":[{},1],"封印的阿巴敦靴的組件":[{},1],"佩勒迪亞靴的圖樣":[{},1],"製作卷軸(佩勒迪亞靴100%)":[{},1],"元素靴的內襯":[{},1],"製作卷軸(元素靴100%)":[{},1],"恩寵靴的內襯":[{},1],"製作卷軸(恩寵靴100%)":[{},1],"寧靜靴的布料":[{},1],"製作卷軸(寧靜靴100%)":[{},1],"祝福靴的組件":[{},1],"製作卷軸(祝福靴100%)":[{},1],"金剛石靴的組件":[{},1],"被遺忘的靴的圖樣":[{},1],"聖恩靴的布料":[{},1],"飛龍皮長靴的組件":[{},1],"全覆式長靴的碎片":[{},1],"覆殼長靴的材料":[{},1],"合金靴的碎片":[{},1],"惡魔長靴的布料":[{},1],"緋紅靴的布料":[{},1],"覆皮長靴的內襯":[{},1],"強化米索莉靴的組件":[{},1],"鏈甲靴的碎片":[{},1],"卡勒米安長靴的組件":[{},1],"金屬皮長靴內襯":[{},1],"矮人鏈靴的碎片":[{},1],"封印長靴的圖樣":[{},1],"襲擊靴的原料":[{},1],"火蜥蜴皮靴的內襯":[{},1],"金屬靴的組件":[{},1],"力量靴的圖樣":[{},1],"刺尾獅皮靴的內襯":[{},1],"鎖子長靴組件":[{},1],"精靈米索莉靴的組件":[{},1],"鋼鐵靴的組件":[{},1],"皮靴的材料":[{},1],"長靴的材料":[{},1],"皮鞋的材料":[{},1],"封印的聖威耳環的寶石":[{},1],"梭芷":[{},1],"封印的不死鳥耳環的寶石":[{},1],"製作卷軸(黑光耳環100%)":[{},1],"黑光耳環的碎片":[{},1],"製作卷軸(金剛石耳環100%)":[{},1],"金剛石耳環的寶石":[{},1],"娜仙耳環的寶石":[{},1],"封印耳環的寶石":[{},1],"守護耳環的寶石":[{},1],"月長石耳環的金屬線":[{},1],"瑪瑙獸眼耳環的寶石":[{},1],"研磨劑":[{},1],"銀鑄模":[{"銀塊":10,"絞線":5,"炭焦":5},1],"精靈耳環的珠子":[{},1],"虎眼耳環的石頭":[{},1],"封印的聖威戒指的寶石":[{},1],"封印的不死鳥戒指的寶石":[{},1],"製作卷軸(黑光戒指100%)":[{},1],"黑光戒指的金屬線":[{},1],"製作卷軸(金剛石戒指100%)":[{},1],"金剛石戒指的金屬線":[{},1],"賢者戒指的寶石":[{},1],"製作卷軸((賢者戒指100%)":[{},1],"封印戒指的寶石":[{},1],"永命戒指的寶石":[{},1],"守護戒指的寶石":[{},1],"水石戒指的金屬線":[{},1],"米索莉戒指的金屬線":[{},1],"精靈戒指的組件":[{},1],"封印的夢魘頭盔的組件":[{},1],"封印的聖威頭箍的組件":[{},1],"封印的黑暗水晶頭盔的組件":[{},1],"封印的塔魯帽的組件":[{},1],"製作卷軸(青狼頭盔100%)":[{},1],"青狼頭盔的組件":[{},1],"製作卷軸(末日頭盔100%)":[{},1],"末日頭盔的圖樣":[{},1],"製作卷軸(夏隆頭盔100%)":[{},1],"夏隆頭盔的組件":[{},1],"製作卷軸(阿巴敦頭箍100%)":[{},1],"阿巴敦頭箍的圖樣":[{},1],"米索莉頭盔的圖樣":[{},1],"全覆式頭盔的組件":[{},1],"合金頭盔的組件":[{},1],"閃耀頭箍的圖樣":[{},1],"巨型頭盔的原料":[{},1],"金屬頭盔的原料":[{},1],"鏈頭巾的圖樣":[{},1],"鎖鏈頭盔的組件":[{},1],"金屬板頭盔的組件":[{},1],"鎖子頭盔的組件":[{},1],"皮頭盔的組件":[{},1],"骨頭盔的組件":[{},1],"封印的夢魘盾碎片":[{},1],"封印的黑暗水晶盾碎片":[{},1],"製作卷軸(末日盾100%)":[{},1],"末日盾的碎片":[{},1],"製作卷軸(夏隆盾100%)":[{},1],"夏隆盾的碎片":[{},1],"製作卷軸(阿巴敦盾100%)":[{},1],"阿巴敦盾的破片":[{},1],"全覆式盾的碎片":[{},1],"厄達拉克塔盾的原料":[{},1],"合金盾的碎片":[{},1],"騎士盾的材料":[{},1],"矮人鏈盾的碎片":[{},1],"鏈盾的碎片":[{},1],"方盾的原料":[{},1],"金屬盾的碎片":[{},1],"鳶形盾的原料":[{},1],"鎖子盾的碎片":[{},1],"封印的聖威項鍊的珠子":[{},1],"封印的不死鳥項鍊的珠子":[{},1],"製作卷軸(黑光項鍊100%)":[{},1],"黑光項鍊的珠子":[{},1],"製作卷軸(金剛石項鍊100%)":[{},1],"金剛石項鍊的鍊子":[{},1],"賢者項鍊的鍊子":[{},1],"製作卷軸(賢者項鍊100%)":[{},1],"封印項鍊的鍊子":[{},1],"人魚之淚的淚珠":[{},1],"守護項鍊的寶石":[{},1],"水石項鍊的鍊子":[{},1],"黑暗項鍊的寶石":[{},1],"精靈項鍊的珠子":[{},1],"魔力項鍊的鍊子":[{},1],"奉獻項鍊的鍊子":[{},1],"藍鑽項鍊的鍊子":[{},1],"智慧項鍊的鍊子":[{},1],"幻滅項鍊的鍊子":[{},1],"奧里哈魯根原石":[{},1],"米索莉原石":[{},1],"鑄模的潤滑劑":[{},1],"鑄模的強化劑":[{},1],"金屬絲":[{"線":10,"鋼鐵礦":5},1],"木炭":[{},1],"金剛石塊":[{},1],"銀塊":[{},1],"鑄模的黏劑":[{},1],"純石":[{},1]}